ðŸŽ¯ Disassembly baÅŸlÄ±yor:

  0           0 RESUME                   0

  1           2 LOAD_CONST               0 (0)
              4 LOAD_CONST               1 (None)
              6 IMPORT_NAME              0 (requests)
              8 STORE_NAME               0 (requests)

  2          10 LOAD_CONST               0 (0)
             12 LOAD_CONST               1 (None)
             14 IMPORT_NAME              1 (webbrowser)
             16 STORE_NAME               1 (webbrowser)

  3          18 LOAD_CONST               0 (0)
             20 LOAD_CONST               2 (('randrange', 'choice'))
             22 IMPORT_NAME              2 (random)
             24 IMPORT_FROM              3 (randrange)
             26 STORE_NAME               3 (randrange)
             28 IMPORT_FROM              4 (choice)
             30 STORE_NAME               4 (choice)
             32 POP_TOP

  4          34 LOAD_CONST               0 (0)
             36 LOAD_CONST               3 (('generate_user_agent',))
             38 IMPORT_NAME              5 (user_agent)
             40 IMPORT_FROM              6 (generate_user_agent)
             42 STORE_NAME               6 (generate_user_agent)
             44 POP_TOP

  5          46 LOAD_CONST               0 (0)
             48 LOAD_CONST               1 (None)
             50 IMPORT_NAME              7 (os)
             52 STORE_NAME               7 (os)

  6          54 LOAD_CONST               0 (0)
             56 LOAD_CONST               1 (None)
             58 IMPORT_NAME              8 (sys)
             60 STORE_NAME               8 (sys)

  7          62 LOAD_CONST               0 (0)
             64 LOAD_CONST               4 (('ThreadPoolExecutor',))
             66 IMPORT_NAME              9 (concurrent.futures)
             68 IMPORT_FROM             10 (ThreadPoolExecutor)
             70 STORE_NAME              10 (ThreadPoolExecutor)
             72 POP_TOP

  8          74 LOAD_CONST               0 (0)
             76 LOAD_CONST               1 (None)
             78 IMPORT_NAME             11 (time)
             80 STORE_NAME              11 (time)

  9          82 LOAD_CONST               0 (0)
             84 LOAD_CONST               5 (('*',))
             86 IMPORT_NAME              2 (random)
             88 IMPORT_STAR

 10          90 LOAD_CONST               0 (0)
             92 LOAD_CONST               1 (None)
             94 IMPORT_NAME              2 (random)
             96 STORE_NAME               2 (random)
             98 LOAD_CONST               0 (0)
            100 LOAD_CONST               1 (None)
            102 IMPORT_NAME             12 (string)
            104 STORE_NAME              12 (string)
            106 LOAD_CONST               0 (0)
            108 LOAD_CONST               1 (None)
            110 IMPORT_NAME             13 (json)
            112 STORE_NAME              13 (json)

 11         114 LOAD_CONST               0 (0)
            116 LOAD_CONST               5 (('*',))
            118 IMPORT_NAME             14 (re)
            120 IMPORT_STAR

 12         122 PUSH_NULL
            124 LOAD_NAME                1 (webbrowser)
            126 LOAD_ATTR               15 (open)
            136 LOAD_CONST               6 ('https://t.me/+QwA1TYem4_wwNmE8')
            138 PRECALL                  1
            142 CALL                     1
            152 POP_TOP

 13         154 BUILD_LIST               0
            156 STORE_NAME              16 (uu)

 15         158 LOAD_CONST               7 ('\x1b[1;31m')
            160 STORE_NAME              17 (E)

 16         162 LOAD_CONST               8 ('\x1b[1;33m')
            164 STORE_NAME              18 (Y)

 17         166 LOAD_CONST               7 ('\x1b[1;31m')
            168 STORE_NAME              19 (Z)

 18         170 LOAD_CONST               8 ('\x1b[1;33m')
            172 STORE_NAME              20 (X)

 19         174 LOAD_CONST               9 ('\x1b[1;32m')
            176 STORE_NAME              21 (BG)

 20         178 LOAD_CONST              10 ('\x1b[2;31m')
            180 STORE_NAME              22 (Z1)

 21         182 LOAD_CONST              11 ('\x1b[2;32m')
            184 STORE_NAME              23 (F)

 22         186 LOAD_CONST              12 ('\x1b[1;34m')
            188 STORE_NAME              24 (BB)

 23         190 LOAD_CONST              13 ('\x1b[2;34m')
            192 STORE_NAME              25 (A)

 24         194 LOAD_CONST              14 ('\x1b[2;35m')
            196 STORE_NAME              26 (C)

 25         198 LOAD_CONST               8 ('\x1b[1;33m')
            200 STORE_NAME              27 (BY)

 26         202 LOAD_CONST              15 ('\x1b[2;36m')
            204 STORE_NAME              28 (S)

 27         206 LOAD_CONST              12 ('\x1b[1;34m')
            208 STORE_NAME              29 (G)

 28         210 LOAD_CONST               7 ('\x1b[1;31m')
            212 STORE_NAME              30 (BR)

 29         214 LOAD_CONST              12 ('\x1b[1;34m')
            216 STORE_NAME              31 (HH)

 30         218 LOAD_CONST              16 ('\x1b[1;37m')
            220 STORE_NAME              32 (M)

 31         222 LOAD_CONST              17 ((0, 0, 0, 0, 0))            224 UNPACK_SEQUENCE          5
            228 STORE_GLOBAL            33 (ge)
            230 STORE_GLOBAL            34 (be)
            232 STORE_GLOBAL            35 (gi)
            234 STORE_GLOBAL            36 (bi)
            236 STORE_GLOBAL            37 (hit)

 32         238 LOAD_NAME               21 (BG)
            240 FORMAT_VALUE             0
            242 LOAD_CONST              18 ('\nâ €â €â €â €â €â €â €â €â €â €â €â €â €â €â €â €â €â €â£€â£ â ¤â €â ’â €â ˆâ ‰â ‰â¢‰â ‰â¡™â ›â ’â ’â ¦â¢„â£€â¡€â €â €â €â €â €â €â €â €â €â €â €â €â €â €â €â €â €â €â €\nâ €â €â €â €â €â €â €â €â €â €â €â €â €â €â£ â¡´â –â ‹â¢â£ â ¤â €â €â €â ‚â â¡ˆâ¢€â â  â â¢ˆâ â¡€â ‚â „â¡‰â ‘â ¶â£¤â¡€â €â €â €â €â €â €â €â €â €â €â €â €â €â €â €\nâ €â €â €â €â €â €â €â €â €â €â €â¡ â ”â ‰â €â¢€â¡¤â šâ ‰â €â €â €â €â â €â ‚â €â „â ‚â¢â ˆâ „â ‚â „â¡â ‚â „â¡â †â¡ â¢™â ³â£¤â¡€â €â €â €â €â €â €â €â €â €â €â €â €\nâ €â €â €â €â €â €â €â €â¢€â¡´â ‹â €â €â €â °â ƒâ €â €â €â €â¢²â €â €â €â ‚â €â¢â  â ˆâ¢€â ‚â Œâ â  â¢€â â¡‚â â¡„â ±â¢Œâ ²â£¡â¢›â¡¶â£„â €â €â €â €â €â €â €â €â €â €\nâ €â €â €â €â €â €â €â¡´â¢«â ‡â €â €â €â €â €â €â €â¢€â£ â¡‡â €â ƒâ£„â €â €â ˆâ €â¡€â â  â €â Œâ  â¢â ‚â¡â  â â „â¡ƒâ¢Žâ¡±â£Œâ ³â¡¼â£¹â¢·â¡€â €â €â €â €â €â €â €â €\nâ €â €â €â €â €â¢ â Žâ¡°â ƒâ €â €â €â €â£€â£ â£´â£¾â¡¿â Ÿâ â €â €â »â£¿â£·â£¶â£¥â£¤â£â£¤â£â£‚â£¡â£€â¡‚â „â ¡â¢ˆâ â¢Œâ ‚â¡µâ¢Œâ¡³â£â¡³â£â¢¿â£†â €â €â €â €â €â €â €\nâ €â €â €â €â¡°â¢ƒâ¡œâ â  â ’â šâ ›â ›â ‰â ‰â â €â €â¢°â –â €â €â €â €â ˆâ ‰â ‰â ‰â ‰â¢‰â ‰â¡‰â â „â¡ˆâ „â¡â ‚â Œâ£€â ³â¡„â¢‡â¡³â¡œâ¡µâ£«â ¾â¡½â£·â¡€â €â €â €â €â €\nâ €â €â €â£°â ‡â¢¸â â €â €â €â €â €â €â €â €â €â €â£ â¡žâ €â €â €â €â €â¢€â €â „â ‚â â ˆâ  â â ‚â „â ¡â¢€â â ‚â „â¡‰â „â¢³â¡ˆâ¢§â¢³â¡±â¢â¡¶â£³â¢»â£§â €â €â €â €â €\nâ €â €â¢ â ‡â¢€â ‡â¡€â €â €â €â €â €â£€â£¤â£´â£¶â£¿â£¿â¡‡â €â €â €â €â €â¢ºâ¡Ÿâ ›â¡›â ›â ›â Ÿâ »â ¿â£·â£¶â£¦â£¬â£â£‚â ˜â£Œâ ¶â£â¡’â¢§â£™â¢®â¢³â£­â£›â¢¾â£§â €â €â €â €\nâ €â €â¡Žâ €â¢¸â €â¢ƒâ£€â£¤â ´â šâ ‰â£‰â£¿â£¿â£¿â£¿â£¿â €â €â €â €â €â â¢€â£‡â €â£·â €â €â €â£¦â£¼â£¿â£¿â£¿â£¿â ™â¢¿â£»â£¼â£½â£½â¢ˆâ ·â£˜â¢Žâ¡—â£²â¡¹â¢®â¡½â¡†â €â €â €\nâ €â¢¸â â¢€â ˜â£´â£¿â ‰â£›â£€â£€â£€â£¹â£¿â£¿â£¿â£¹â£¿â €â €â¢€â €â â¡€â ‚â£¿â¡€â ˜â¢†â£€â£€â£ˆâ£»â£¿â£¿â£¿â£ƒâ €â  â ˆâ£¹â£¿â£¿â Œâ£Žâ µâ£ªâ ¼â£¡â¢›â ¦â¡â£¿â¡€â €â €\nâ €â¡â €â „â¡€â ‹â ‰â ‰â â €â €â €â €â €â €â ˆâ ›â ›â €â €â¡€â €â ‚â €â ´â ¿â ‰â â ©â ‰â â¡‰â¢‰â ‰â¡‰â¢‰â ‰â¡‰â¢‰â ›â ›â »â¢¿â¡œâ¢¤â ›â£”â¢«â –â¡­â¢šâ¡±â£½â¡‡â €â €\nâ €â¡‡â¡ˆâ „â â ˆâ¡€â ‚â â €â ‚â â €â ‚â ˆâ €â „â €â¡â €â¡€â ‚â¢â ˆâ  â €â Œâ  â¢â ˆâ „â¡€â¢‚â â¡€â¢‚â â¡€â ‚â Œâ Œâ¡…â¢Šâ â¡¢â â£¬â “â¢®â¡‘â¢£â •â¡®â¡‡â €â €\nâ¢€â¡‡â â¡ˆâ  â¢â  â¢ˆâ €â ¡â ˆâ¡€â Œâ €â¡â â¡€â â¡€â â¢€â â¡€â Œâ¢€â ¡â ˆâ¡â  â¢ˆâ â¡€â¢‚â â¡ˆâ „â¡‰â „â ¡â¡ˆâ °â¢ˆâ¢†â¢©â ’â¡â ¶â¡™â¢¦â ™â¡¢â â£œâ£·â €â €\nâ¢°â¡‡â ¡â¢€â ¡â¢€â ‚â „â¡ˆâ â  â €â „â¡â¢€â ‚â „â ‚â  â£â ‚â  â¢€â ‚â „â ‚â¡â â¡€â¢‚â â¡€â¢‚â â¡€â¢‚â â¡ˆâ ¡â¢€â £â Œâ¡Œâ¢¢â â£Œâ ³â£‰â ¦â£™â °â£©â¢²â¡‡â €â €\nâ €â£‡â ‚â „â ‚â „â¡ˆâ â  â¢â ‚â¢â£‚â£¤â£¤â£¤â£€â¡¤â ¦â¢¤â£â¢£â¡€â ‚â Œâ¡â  â¢â â¡€â¢‚â â¡€â¢‚â â  â ‚â¡„â¢ƒâ ‚â£…â¡šâ£Œâ¢£â žâ£”â£‹â –â¡‘â¢†â¡ƒâ¢†â£³â¡‡â €â €\nâ €â¢¸â¡Žâ  â¡â ‚â „â¡â ‚â „â£¼â£‹â£¤â¡€â¡€â €â£€â£€â£ â£€â ˆâ ³â£·â¡ˆâ â  â¢â ‚â¡â¢€â ‚â¡â¢€â ‚â£Œâ¡°â£¡â œâ£Œâ ³â£„â ³â£Œâ –â£â¢²â¡˜â¢¬â¡‘â¢¢â ˜â¡¬â£¾â â €â €\nâ €â ˆâ£·â¡â ¤â¡‰â¢‚â ¤â¢â Œâ¢¿â¡˜â ›â ›â ›â¢‰â ›â ¹â ›â ‹â ·â¢¦â ¹â¢·â ˆâ¡â¢€â ‚â¡â¢€â¢‚â¡´â£Šâ žâ¡´â£“â ´â£©â ’â¡µâ£ˆâ —â¡¬â¡šâ£Œâ ²â£‰â¢†â¡˜â „â£ƒâ¢¶â ‡â €â €â €\nâ €â €â ˜â£—â¡¢â â¡œâ ¤â£‰â ¦â¡œâ¢¿â£¶â£¶â£¶â£¦â£¶â£¶â£¾â¡´â¢¢â â£§â €â ¡â â¡€â¢‚â¡´â£‹â ¾â£”â¡«â£â ²â£â¢žâ¡¡â¢«â ´â£‰â žâ¡°â¢©â †â¡“â¢„â ¢â â Œâ ¤â¡Ÿâ €â €â¡„â¢€\nâ €â €â €â ¹â£§â¡™â£Œâ ³â¡Œâ¢Žâ¡™â ¦â£‰â â »â¡™â¢â ›â ¥â¢‹â ‡â šâ¡˜â  â¢â ‚â¡â£§â žâ£­â¡“â¢®â¡±â¢Žâ ³â¡œâ¡Œâ¢–â¡±â¢Šâ£´â ›â¢»â¡‡â ˜â¡â¢€â ‚â ¡â¢ˆâ¡¾â €â €â¢ â ƒâ¢¸\nâ €â €â €â €â ˜â£·â¡Œâ¢³â¡¸â£Œâ¢±â¢£â¡â¢Œâ ±â ˆâ¡„â ¨â â  â ˆâ ¥â¢€â¢â ¢â¢â¡¹â£œâ¡»â¢¦â¡™â¢§â ±â¡â¢£â ±â¢œâ ¢â¡±â¢¹â£¿â €â¢ â£‡â ¡â â  â ˆâ¢„â¡Ÿâ â €â¢€â Žâ¢ â ‡\nâ €â €â €â €â €â ˆâ¢»â£¥â ²â¡œâ£Šâ¢¦â ±â¡ˆâ¢†â¡±â¢€â¢ƒâ ©â¡â¢¡â ‚â¡…â¢‚â †â¡¡â£Ÿâ¡¼â£“â¢§â¡¹â£Œâ¡“â£Œâ¢£â¡™â ¢â¢ƒâ ”â¡©â£¿â €â €â¢¿â €â¡â¢‚â£¡â ‹â €â¢€â¡´â ƒâ£ â â €\nâ €â €â €â €â €â €â €â ™â¢·â¡˜â¢¤â ‹â¢–â ¡â¢‚â ”â£ˆâ¢‚â ‘â¡ˆâ¢†â ’â¡˜â¡„â¢šâ °â£¹â¡šâ¡µâ£Šâ¡•â¢¢â¡‘â¢‚â †â¡Œâ ¡â¢‚â â  â¢¹â €â €â ˜â£†â£°â žâ â  â ”â ‰â£ â –â â €â €\nâ €â €â €â €â €â €â €â €â ˆâ ³â£Œâ ’â Œâ ‚â Œâ  â ‰â Œâ¡â ¡â Œâ¡°â ¡â ‘â¡Œâ ¢â¢â¡³â¢¥â¢‹â •â¡Šâ ±â ˆâ „â¡â ‚â Œâ¡â  â ˜â¡†â €â €â£¿â ‹â €â €â¢€â¡ â ”â ‹â €â €â €â €\nâ €â €â €â €â €â €â €â €â €â €â ˆâ ‘â¢®â£„â ¡â â Œâ¡â  â¢â ‚â „â ¡â¢â °â¢â Šâ Œâ¡‘â Šâ¢„â â¡‚â¢±â¡â ™â¢³â£¤â ´â ’â ‹â ‰â ‰â ‘â šâ ¦â¡€â €â €â €â €â €â €â €â €â €\nâ €â €â €â €â €â €â €â €â €â €â €â €â €â ˆâ ‘â £â¢†â¡„â¡â ‚â Œâ  â¢â ‚â¡â  â¢ˆâ â  â¢â ‚â¡â  â ‰â ³â£„â£ºâ¡€â €â¢€â£€â¡¤â ¤â ¤â£€â£€â ˆâ¢£â¡€â €â €â €â €â €â €â €\nâ €â €â €â €â €â €â €â €â €â €â €â €â €â €â €â €â €â ‰â »â£¶â£¬â£â£€â ‚â €â â ‚â ˆâ €â €â£€â£€â£€â£¤â£´â£¿â£¿â£¿â£¿â Ÿâ¡‡â €â €â €â €â €â €â €â£³â¡€â €â €â €â €â €â €\nâ €â €â €â €â €â €â €â €â €â €â €â €â €â €â €â €â €â €â €â €â €â ‰â ‰â ›â ›â ›â ›â ›â ›â ›â ‰â ‹â ‰â â €â €â ™â¢»â¡â¢ˆâ¢™â¡¶â –â ’â ‹â ‰â ‰â ‰â ¹â£·â €â €â €â €â €â €\nâ €â €â €â €â €â €â €â €â €â €â €â €â €â €â €â €â €â €â €â €â €â €â €â €â €â €â €â €â €â €â €â €â €â €â €â €â €â ˆâ£‡â£¼â¡žâ  â£€â¡€â €â €â €â €â£°â£¿â €â €â €â €â €â €\nâ €â €â €â €â €â €â €â €â €â €â €â €â €â €â €â €â €â €â €â €â €â €â €â €â €â €â €â €â €â €â €â €â €â €â €â €â €â €â ™â ¿â£‡â ¦â£ â£¿â£¶â¢¦â ¤â¢€â£¿â â €â €â €â €â €â €\nâ €â €â €â €â €â €â €â €â €â €â €â €â €â €â €â €â €â €â €â €â €â €â €â €â €â €â €â €â €â €â €â €â €â €â €â €â €â €â €â €â ˆâ ™â£¿â£¿â£‡â£¤â¡¶â Ÿâ ‰â €â €â €â €â €â €â €\n\n\n')

 66         244 LOAD_NAME               31 (HH)

 32         246 FORMAT_VALUE             0
            248 LOAD_CONST              19 ('\n')

 67         250 LOAD_NAME               20 (X)

 32         252 FORMAT_VALUE             0
            254 LOAD_CONST              20 (' DEV ')

 67         256 LOAD_NAME               27 (BY)

 32         258 FORMAT_VALUE             0
            260 LOAD_CONST              21 ('@Rolexwhat\n')

 68         262 LOAD_NAME               31 (HH)

 32         264 FORMAT_VALUE             0
            266 LOAD_CONST              22 ('\n ')
            268 BUILD_STRING            10
            270 STORE_NAME              38 (kkk)

 70         272 PUSH_NULL
            274 LOAD_NAME               39 (print)
            276 LOAD_NAME               38 (kkk)
            278 PRECALL                  1
            282 CALL                     1
            292 POP_TOP

 71         294 PUSH_NULL
            296 LOAD_NAME               40 (input)
            298 LOAD_NAME               24 (BB)
            300 LOAD_CONST              23 ('ID : ')
            302 BINARY_OP                0 (+)
            306 LOAD_NAME               17 (E)
            308 BINARY_OP                0 (+)
            312 PRECALL                  1
            316 CALL                     1
            326 STORE_NAME              41 (iid)

 72         328 PUSH_NULL
            330 LOAD_NAME               40 (input)
            332 LOAD_NAME               30 (BR)
            334 LOAD_CONST              24 ('TOKEN : ')
            336 BINARY_OP                0 (+)
            340 LOAD_NAME               17 (E)
            342 BINARY_OP                0 (+)
            346 PRECALL                  1
            350 CALL                     1
            360 STORE_NAME              42 (tok)

 73         362 PUSH_NULL
            364 LOAD_NAME                7 (os)
            366 LOAD_ATTR               43 (system)
            376 LOAD_NAME                7 (os)
            378 LOAD_ATTR               44 (name)
            388 LOAD_CONST              25 ('nt')
            390 COMPARE_OP               2 (==)
            396 POP_JUMP_FORWARD_IF_FALSE     2 (to 402)
            398 LOAD_CONST              26 ('cls')
            400 JUMP_FORWARD             1 (to 404)
        >>  402 LOAD_CONST              27 ('clear')
        >>  404 PRECALL                  1
            408 CALL                     1
            418 POP_TOP

 74         420 LOAD_CONST              28 ('')
            422 LOAD_METHOD             45 (join)
            444 LOAD_CONST              29 (<code object <genexpr> at 0x7c58771930, file "module", line 74>)
            446 MAKE_FUNCTION            0
            448 PUSH_NULL
            450 LOAD_NAME               46 (range)
            452 LOAD_CONST              30 (8)
            454 PRECALL                  1
            458 CALL                     1
            468 GET_ITER
            470 PRECALL                  0
            474 CALL                     0
            484 PRECALL                  1
            488 CALL                     1
            498 STORE_NAME              47 (tlg)

 76         500 PUSH_NULL
            502 LOAD_NAME                7 (os)
            504 LOAD_ATTR               43 (system)
            514 LOAD_CONST              27 ('clear')
            516 PRECALL                  1
            520 CALL                     1
            530 POP_TOP

 77         532 LOAD_CONST              31 (<code object rest at 0x7db890b290, file "module", line 77>)
            534 MAKE_FUNCTION            0
            536 STORE_NAME              48 (rest)

110         538 LOAD_CONST              32 (<code object date at 0x7dd892b930, file "module", line 110>)
            540 MAKE_FUNCTION            0
            542 STORE_NAME              49 (date)

136         544 LOAD_CONST              33 (<code object info at 0x7de8914af0, file "module", line 136>)
            546 MAKE_FUNCTION            0
            548 STORE_NAME              50 (info)

211         550 LOAD_CONST              34 (<code object gmail at 0x7df890d010, file "module", line 211>)
            552 MAKE_FUNCTION            0
            554 STORE_NAME              51 (gmail)

343         556 LOAD_CONST              35 (<code object hott at 0x7de8915160, file "module", line 343>)
            558 MAKE_FUNCTION            0
            560 STORE_NAME              52 (hott)

364         562 LOAD_CONST              36 (<code object insta2 at 0x7de891f8c0, file "module", line 364>)
            564 MAKE_FUNCTION            0
            566 STORE_NAME              53 (insta2)

408         568 LOAD_CONST              37 (<code object insta at 0x7de891e570, file "module", line 408>)
            570 MAKE_FUNCTION            0
            572 STORE_NAME              54 (insta)

451         574 LOAD_CONST              38 (<code object random1 at 0x7dd892dbb0, file "module", line 451>)
            576 MAKE_FUNCTION            0
            578 STORE_NAME              55 (random1)

535         580 LOAD_CONST              39 (<code object ee at 0x7dc892b9d0, file "module", line 535>)
            582 MAKE_FUNCTION            0
            584 STORE_NAME              56 (ee)

545         586 LOAD_CONST              40 (<code object hot at 0x7dc892d910, file "module", line 545>)
            588 MAKE_FUNCTION            0
            590 STORE_NAME              57 (hot)

555         592 LOAD_CONST              41 (<code object znm at 0x7de891b860, file "module", line 555>)
            594 MAKE_FUNCTION            0
            596 STORE_NAME              58 (znm)

643         598 PUSH_NULL
            600 LOAD_NAME               58 (znm)
            602 PRECALL                  0
            606 CALL                     0
            616 POP_TOP
            618 LOAD_CONST               1 (None)
            620 RETURN_VALUE

Disassembly of <code object <genexpr> at 0x7c58771930, file "module", line 74>:
 74           0 RETURN_GENERATOR
              2 POP_TOP
              4 RESUME                   0
              6 LOAD_FAST                0 (.0)
        >>    8 FOR_ITER                24 (to 58)
             10 STORE_FAST               1 (i)
             12 LOAD_GLOBAL              1 (NULL + random)
             24 LOAD_ATTR                1 (choice)
             34 LOAD_CONST               0 ('QWERTYUIOPASDFGHJKLZXCVBNM')
             36 PRECALL                  1
             40 CALL                     1
             50 YIELD_VALUE
             52 RESUME                   1
             54 POP_TOP
             56 JUMP_BACKWARD           25 (to 8)
        >>   58 LOAD_CONST               1 (None)
             60 RETURN_VALUE

Disassembly of <code object rest at 0x7db890b290, file "module", line 77>:
 77           0 RESUME                   0

 78           2 LOAD_FAST                0 (email)
              4 LOAD_METHOD              0 (split)
             26 LOAD_CONST               1 ('@')
             28 PRECALL                  1
             32 CALL                     1
             42 LOAD_CONST               2 (0)
             44 BINARY_SUBSCR
             54 STORE_FAST               1 (rre)

 79          56 LOAD_CONST               3 ('https://i.instagram.com/api/v1/accounts/send_recovery_flow_email/')
             58 STORE_FAST               2 (uh)

 80          60 BUILD_MAP                0

 81          62 LOAD_CONST               4 ('X-Pigeon-Session-Id')
             64 LOAD_CONST               5 ('2b712457-ffad-4dba-9241-29ea2f472ac5')

 80          66 MAP_ADD                  1

 82          68 LOAD_CONST               6 ('X-Pigeon-Rawclienttime')
             70 LOAD_CONST               7 ('1707104597.347')

 80          72 MAP_ADD                  1

 83          74 LOAD_CONST               8 ('X-IG-Connection-Speed')
             76 LOAD_CONST               9 ('-1kbps')

 80          78 MAP_ADD                  1

 84          80 LOAD_CONST              10 ('X-IG-Bandwidth-Speed-KBPS')
             82 LOAD_CONST              11 ('-1.000')

 80          84 MAP_ADD                  1

 85          86 LOAD_CONST              12 ('X-IG-Bandwidth-TotalBytes-B')
             88 LOAD_CONST              13 ('0')

 80          90 MAP_ADD                  1

 86          92 LOAD_CONST              14 ('X-IG-Bandwidth-TotalTime-MS')
             94 LOAD_CONST              13 ('0')

 80          96 MAP_ADD                  1

 87          98 LOAD_CONST              15 ('X-IG-VP9-Capable')
            100 LOAD_CONST              16 ('false')

 80         102 MAP_ADD                  1

 88         104 LOAD_CONST              17 ('X-Bloks-Version-Id')
            106 LOAD_CONST              18 ('009f03b18280bb343b0862d663f31ac80c5fb30dfae9e273e43c63f13a9f31c0')

 80         108 MAP_ADD                  1

 89         110 LOAD_CONST              19 ('X-IG-Connection-Type')
            112 LOAD_CONST              20 ('WIFI')

 80         114 MAP_ADD                  1

 90         116 LOAD_CONST              21 ('X-IG-Capabilities')
            118 LOAD_CONST              22 ('3brTvw==')

 80         120 MAP_ADD                  1

 91         122 LOAD_CONST              23 ('X-IG-App-ID')
            124 LOAD_CONST              24 ('567067343352427')

 80         126 MAP_ADD                  1

 92         128 LOAD_CONST              25 ('User-Agent')
            130 LOAD_CONST              26 ('Instagram 100.0.0.17.129 Android (30/11; 320dpi; 720x1448; realme; RMX3231; RMX3231; RMX3231; ar_IQ; 161478664)')

 80         132 MAP_ADD                  1

 93         134 LOAD_CONST              27 ('Accept-Language')
            136 LOAD_CONST              28 ('ar-IQ, en-US')

 80         138 MAP_ADD                  1

 94         140 LOAD_CONST              29 ('Cookie')
            142 LOAD_CONST              30 ('mid=Zbu4xQABAAE0k2Ok6rVxXpTD8PFQ; csrftoken=dG4dEIkWvAWpIj1B2M2mutWtdO1LiPCK')

 80         144 MAP_ADD                  1

 95         146 LOAD_CONST              31 ('Content-Type')
            148 LOAD_CONST              32 ('application/x-www-form-urlencoded; charset=UTF-8')

 80         150 MAP_ADD                  1

 96         152 LOAD_CONST              33 ('Accept-Encoding')
            154 LOAD_CONST              34 ('gzip, deflate')
 80         156 MAP_ADD                  1

 97         158 LOAD_CONST              35 ('Host')
            160 LOAD_CONST              36 ('i.instagram.com')

 80         162 MAP_ADD                  1

 98         164 LOAD_CONST              37 ('Liger')

 99         166 LOAD_CONST              38 ('keep-alive')

100         168 LOAD_CONST              39 ('364')

 80         170 LOAD_CONST              40 (('X-FB-HTTP-Engine', 'Connection', 'Content-Length'))
            172 BUILD_CONST_KEY_MAP      3
            174 DICT_UPDATE              1
            176 STORE_FAST               3 (hr)

103         178 LOAD_CONST              41 ('ef02f559b04e8d7cbe15fb8cf18e2b48fb686dafd056b7c9298c08f3e2007d43.{"_csrftoken":"dG4dEIkWvAWpIj1B2M2mutWtdO1LiPCK","adid":"5e7df201-a1ff-45ec-8107-31b10944e25c","guid":"b0382b46-1663-43a7-ba90-3949c43fd808","device_id":"android-71a5d65f74b8fcbc","query":"')
            180 LOAD_FAST                1 (rre)
            182 FORMAT_VALUE             0
            184 LOAD_CONST              42 ('"}')
            186 BUILD_STRING             3

105         188 LOAD_CONST              43 ('4')

102         190 LOAD_CONST              44 (('signed_body', 'ig_sig_key_version'))
            192 BUILD_CONST_KEY_MAP      2
            194 STORE_FAST               4 (dah)

107         196 LOAD_GLOBAL              3 (NULL + requests)            208 LOAD_ATTR                2 (post)
            218 LOAD_FAST                2 (uh)
            220 LOAD_FAST                3 (hr)
            222 LOAD_FAST                4 (dah)
            224 KW_NAMES                45
            226 PRECALL                  3
            230 CALL                     3
            240 LOAD_ATTR                3 (text)
            250 STORE_FAST               5 (k)

108         252 LOAD_FAST                5 (k)
            254 LOAD_METHOD              0 (split)
            276 LOAD_CONST              46 ('email":"')
            278 PRECALL                  1
            282 CALL                     1
            292 LOAD_CONST              47 (1)
            294 BINARY_SUBSCR
            304 LOAD_METHOD              0 (split)
            326 LOAD_CONST              48 ('","status":"ok"}')
            328 PRECALL                  1
            332 CALL                     1
            342 LOAD_CONST               2 (0)
            344 BINARY_SUBSCR
            354 RETURN_VALUE
        >>  356 PUSH_EXC_INFO

109         358 POP_TOP
            360 POP_EXCEPT
            362 LOAD_CONST              49 (False)
            364 RETURN_VALUE
        >>  366 COPY                     3
            368 POP_EXCEPT
            370 RERAISE                  1
ExceptionTable:
  252 to 352 -> 356 [0]
  356 to 358 -> 366 [1] lasti

Disassembly of <code object date at 0x7dd892b930, file "module", line 110>:
110           0 RESUME                   0

111           2 NOP

112           4 LOAD_GLOBAL              1 (NULL + int)
             16 LOAD_FAST                0 (Id)
             18 PRECALL                  1
             22 CALL                     1
             32 LOAD_CONST               1 (1545545)
             34 COMPARE_OP               4 (>)
             40 POP_JUMP_FORWARD_IF_FALSE    21 (to 84)
             42 LOAD_GLOBAL              1 (NULL + int)
             54 LOAD_FAST                0 (Id)
             56 PRECALL                  1
             60 CALL                     1
             70 LOAD_CONST               2 (1279000)
             72 COMPARE_OP               0 (<)
             78 POP_JUMP_FORWARD_IF_FALSE     2 (to 84)

113          80 LOAD_CONST               3 (2010)
             82 RETURN_VALUE

114     >>   84 LOAD_GLOBAL              1 (NULL + int)
             96 LOAD_FAST                0 (Id)
             98 PRECALL                  1
            102 CALL                     1
            112 LOAD_CONST               4 (1279001)
            114 COMPARE_OP               4 (>)
            120 POP_JUMP_FORWARD_IF_FALSE    21 (to 164)
            122 LOAD_GLOBAL              1 (NULL + int)
            134 LOAD_FAST                0 (Id)
            136 PRECALL                  1
            140 CALL                     1
            150 LOAD_CONST               5 (17750000)
            152 COMPARE_OP               0 (<)
            158 POP_JUMP_FORWARD_IF_FALSE     2 (to 164)

115         160 LOAD_CONST               6 (2011)
            162 RETURN_VALUE

116     >>  164 LOAD_GLOBAL              1 (NULL + int)
            176 LOAD_FAST                0 (Id)
            178 PRECALL                  1
            182 CALL                     1
            192 LOAD_CONST               7 (17750001)
            194 COMPARE_OP               4 (>)
            200 POP_JUMP_FORWARD_IF_FALSE    21 (to 244)
            202 LOAD_GLOBAL              1 (NULL + int)
            214 LOAD_FAST                0 (Id)
            216 PRECALL                  1
            220 CALL                     1
            230 LOAD_CONST               8 (279760000)
            232 COMPARE_OP               0 (<)
            238 POP_JUMP_FORWARD_IF_FALSE     2 (to 244)

117         240 LOAD_CONST               9 (2012)
            242 RETURN_VALUE

118     >>  244 LOAD_GLOBAL              1 (NULL + int)
            256 LOAD_FAST                0 (Id)
            258 PRECALL                  1
            262 CALL                     1
            272 LOAD_CONST              10 (279760001)
            274 COMPARE_OP               4 (>)
            280 POP_JUMP_FORWARD_IF_FALSE    21 (to 324)
            282 LOAD_GLOBAL              1 (NULL + int)
            294 LOAD_FAST                0 (Id)
            296 PRECALL                  1
            300 CALL                     1
            310 LOAD_CONST              11 (900990000)
            312 COMPARE_OP               0 (<)
            318 POP_JUMP_FORWARD_IF_FALSE     2 (to 324)

119         320 LOAD_CONST              12 (2013)
            322 RETURN_VALUE

120     >>  324 LOAD_GLOBAL              1 (NULL + int)
            336 LOAD_FAST                0 (Id)
            338 PRECALL                  1
            342 CALL                     1
            352 LOAD_CONST              13 (900990001)
            354 COMPARE_OP               4 (>)
            360 POP_JUMP_FORWARD_IF_FALSE    21 (to 404)
            362 LOAD_GLOBAL              1 (NULL + int)
            374 LOAD_FAST                0 (Id)
            376 PRECALL                  1
            380 CALL                     1
            390 LOAD_CONST              14 (1629010000)
            392 COMPARE_OP               0 (<)
            398 POP_JUMP_FORWARD_IF_FALSE     2 (to 404)

121         400 LOAD_CONST              15 (2014)
            402 RETURN_VALUE

122     >>  404 LOAD_GLOBAL              1 (NULL + int)
            416 LOAD_FAST                0 (Id)
            418 PRECALL                  1
            422 CALL                     1
            432 LOAD_CONST              16 (1900000000)
            434 COMPARE_OP               4 (>)
            440 POP_JUMP_FORWARD_IF_FALSE    21 (to 484)
            442 LOAD_GLOBAL              1 (NULL + int)
            454 LOAD_FAST                0 (Id)
            456 PRECALL                  1
            460 CALL                     1
            470 LOAD_CONST              17 (2500000000)
            472 COMPARE_OP               0 (<)
            478 POP_JUMP_FORWARD_IF_FALSE     2 (to 484)

123         480 LOAD_CONST              18 (2015)
            482 RETURN_VALUE

124     >>  484 LOAD_GLOBAL              1 (NULL + int)
            496 LOAD_FAST                0 (Id)
            498 PRECALL                  1
            502 CALL                     1
            512 LOAD_CONST              17 (2500000000)
            514 COMPARE_OP               4 (>)
            520 POP_JUMP_FORWARD_IF_FALSE    21 (to 564)
            522 LOAD_GLOBAL              1 (NULL + int)
            534 LOAD_FAST                0 (Id)
            536 PRECALL                  1
            540 CALL                     1
            550 LOAD_CONST              19 (3713668786)
            552 COMPARE_OP               0 (<)
            558 POP_JUMP_FORWARD_IF_FALSE     2 (to 564)

125         560 LOAD_CONST              20 (2016)
            562 RETURN_VALUE

126     >>  564 LOAD_GLOBAL              1 (NULL + int)
            576 LOAD_FAST                0 (Id)
            578 PRECALL                  1
            582 CALL                     1
            592 LOAD_CONST              19 (3713668786)
            594 COMPARE_OP               4 (>)
            600 POP_JUMP_FORWARD_IF_FALSE    21 (to 644)
            602 LOAD_GLOBAL              1 (NULL + int)
            614 LOAD_FAST                0 (Id)
            616 PRECALL                  1
            620 CALL                     1
            630 LOAD_CONST              21 (5699785217)
            632 COMPARE_OP               0 (<)
            638 POP_JUMP_FORWARD_IF_FALSE     2 (to 644)

127         640 LOAD_CONST              22 (2017)
            642 RETURN_VALUE

128     >>  644 LOAD_GLOBAL              1 (NULL + int)
            656 LOAD_FAST                0 (Id)
            658 PRECALL                  1
            662 CALL                     1
            672 LOAD_CONST              21 (5699785217)
            674 COMPARE_OP               4 (>)
            680 POP_JUMP_FORWARD_IF_FALSE    21 (to 724)
            682 LOAD_GLOBAL              1 (NULL + int)
            694 LOAD_FAST                0 (Id)
            696 PRECALL                  1
            700 CALL                     1
            710 LOAD_CONST              23 (8507940634)
            712 COMPARE_OP               0 (<)
            718 POP_JUMP_FORWARD_IF_FALSE     2 (to 724)

129         720 LOAD_CONST              24 (2018)
            722 RETURN_VALUE

130     >>  724 LOAD_GLOBAL              1 (NULL + int)
            736 LOAD_FAST                0 (Id)
            738 PRECALL                  1
            742 CALL                     1
            752 LOAD_CONST              23 (8507940634)
            754 COMPARE_OP               4 (>)
            760 POP_JUMP_FORWARD_IF_FALSE    21 (to 804)
            762 LOAD_GLOBAL              1 (NULL + int)
            774 LOAD_FAST                0 (Id)
            776 PRECALL                  1
            780 CALL                     1
            790 LOAD_CONST              25 (21254029834)
            792 COMPARE_OP               0 (<)
            798 POP_JUMP_FORWARD_IF_FALSE     2 (to 804)

131         800 LOAD_CONST              26 (2019)
            802 RETURN_VALUE

133     >>  804 LOAD_CONST              27 ('2020-2023')
            806 RETURN_VALUE
        >>  808 PUSH_EXC_INFO

134         810 POP_TOP

135         812 POP_EXCEPT
            814 LOAD_CONST              28 (False)
            816 RETURN_VALUE
        >>  818 COPY                     3
            820 POP_EXCEPT
            822 RERAISE                  1
ExceptionTable:
  4 to 78 -> 808 [0]
  84 to 158 -> 808 [0]
  164 to 238 -> 808 [0]
  244 to 318 -> 808 [0]
  324 to 398 -> 808 [0]
  404 to 478 -> 808 [0]
  484 to 558 -> 808 [0]
  564 to 638 -> 808 [0]
  644 to 718 -> 808 [0]
  724 to 798 -> 808 [0]
  808 to 810 -> 818 [1] lasti

Disassembly of <code object info at 0x7de8914af0, file "module", line 136>:
136           0 RESUME                   0

138           2 LOAD_GLOBAL              0 (hit)
             14 LOAD_CONST               1 (1)
             16 BINARY_OP               13 (+=)
             20 STORE_GLOBAL             0 (hit)

139          22 LOAD_GLOBAL              3 (NULL + rest)
             34 LOAD_FAST                0 (email)
             36 PRECALL                  1
             40 CALL                     1
             50 STORE_FAST               1 (res)

140          52 LOAD_FAST                0 (email)
             54 LOAD_METHOD              2 (split)
             76 LOAD_CONST               2 ('@')
             78 PRECALL                  1
             82 CALL                     1
             92 LOAD_CONST               3 (0)
             94 BINARY_SUBSCR
            104 STORE_FAST               2 (username)

141         106 NOP

143         108 LOAD_CONST               4 ('https://i.instagram.com/api/v1/users/web_profile_info/?username=')
            110 LOAD_FAST                2 (username)
            112 FORMAT_VALUE             0
            114 BUILD_STRING             2
            116 STORE_FAST               3 (url)

145         118 LOAD_CONST               5 ('Mozilla/5.0 (Windows NT 10.0; Win64; x64) AppleWebKit/537.36')

146         120 LOAD_CONST               6 ('936619743392459')

147         122 LOAD_CONST               7 ('*/*')

148         124 LOAD_CONST               8 ('en-US,en;q=0.9')

149         126 LOAD_CONST               9 ('gzip, deflate, br')

150         128 LOAD_CONST              10 ('keep-alive')

144         130 LOAD_CONST              11 (('User-Agent', 'X-IG-App-ID', 'Accept', 'Accept-Language', 'Accept-Encoding', 'Connection'))
            132 BUILD_CONST_KEY_MAP      6
            134 STORE_FAST               4 (headers)

153         136 LOAD_GLOBAL              7 (NULL + requests)            148 LOAD_ATTR                4 (get)
            158 LOAD_FAST                3 (url)
            160 LOAD_FAST                4 (headers)
            162 KW_NAMES                12
            164 PRECALL                  2
            168 CALL                     2
            178 STORE_FAST               5 (response)

156         180 LOAD_FAST                5 (response)
            182 LOAD_ATTR                5 (status_code)
            192 LOAD_CONST              13 (200)
            194 COMPARE_OP               3 (!=)
            200 POP_JUMP_FORWARD_IF_FALSE     1 (to 204)

157         202 NOP

159     >>  204 LOAD_FAST                5 (response)
            206 LOAD_METHOD              6 (json)
            228 PRECALL                  0
            232 CALL                     0
            242 STORE_FAST               6 (data)

160         244 LOAD_FAST                6 (data)
            246 LOAD_CONST              14 ('data')
            248 BINARY_SUBSCR
            258 LOAD_CONST              15 ('user')
            260 BINARY_SUBSCR
            270 STORE_FAST               7 (user)

164         272 LOAD_FAST                7 (user)
            274 LOAD_CONST              16 ('username')
            276 BINARY_SUBSCR

165         286 LOAD_FAST                7 (user)
            288 LOAD_CONST              17 ('id')
            290 BINARY_SUBSCR

166         300 LOAD_FAST                7 (user)
            302 LOAD_CONST              18 ('full_name')
            304 BINARY_SUBSCR

167         314 LOAD_FAST                7 (user)
            316 LOAD_CONST              19 ('edge_followed_by')
            318 BINARY_SUBSCR
            328 LOAD_CONST              20 ('count')
            330 BINARY_SUBSCR

168         340 LOAD_FAST                7 (user)
            342 LOAD_CONST              21 ('edge_follow')
            344 BINARY_SUBSCR
            354 LOAD_CONST              20 ('count')
            356 BINARY_SUBSCR

169         366 LOAD_FAST                7 (user)
            368 LOAD_CONST              22 ('edge_owner_to_timeline_media')
            370 BINARY_SUBSCR
            380 LOAD_CONST              20 ('count')
            382 BINARY_SUBSCR

170         392 LOAD_FAST                7 (user)
            394 LOAD_CONST              23 ('biography')
            396 BINARY_SUBSCR

171         406 LOAD_FAST                7 (user)
            408 LOAD_CONST              24 ('is_private')
            410 BINARY_SUBSCR

172         420 LOAD_FAST                7 (user)
            422 LOAD_CONST              25 ('is_verified')
            424 BINARY_SUBSCR

173         434 LOAD_FAST                7 (user)
            436 LOAD_CONST              26 ('profile_pic_url')
            438 BINARY_SUBSCR

163         448 LOAD_CONST              27 (('username', 'Id', 'full_name', 'followers', 'following', 'posts', 'bio', 'is_private', 'is_verified', 'profile_pic_url'))
            450 BUILD_CONST_KEY_MAP     10
            452 STORE_FAST               8 (user_info)

175         454 LOAD_FAST                8 (user_info)
            456 LOAD_CONST              28 ('Id')
            458 BINARY_SUBSCR
            468 STORE_FAST               9 (Id)

176         470 LOAD_FAST                8 (user_info)
            472 LOAD_CONST              18 ('full_name')
            474 BINARY_SUBSCR
            484 STORE_FAST              10 (full_name)

177         486 LOAD_FAST                8 (user_info)
            488 LOAD_CONST              29 ('followers')
            490 BINARY_SUBSCR
            500 STORE_FAST              11 (followers)

178         502 LOAD_FAST                8 (user_info)
            504 LOAD_CONST              30 ('following')
            506 BINARY_SUBSCR
            516 STORE_FAST              12 (following)

179         518 LOAD_FAST                8 (user_info)
            520 LOAD_CONST              31 ('posts')
            522 BINARY_SUBSCR
            532 STORE_FAST              13 (posts)

180         534 LOAD_FAST                8 (user_info)
            536 LOAD_CONST              32 ('bio')
            538 BINARY_SUBSCR
            548 STORE_FAST              14 (bio)

181         550 LOAD_FAST                8 (user_info)
            552 LOAD_CONST              25 ('is_verified')
            554 BINARY_SUBSCR
            564 STORE_FAST              15 (is_verified)

182         566 LOAD_FAST                8 (user_info)
            568 LOAD_CONST              24 ('is_private')
            570 BINARY_SUBSCR
            580 STORE_FAST              16 (is_private)

183         582 LOAD_FAST                8 (user_info)
            584 LOAD_CONST              26 ('profile_pic_url')
            586 BINARY_SUBSCR
            596 STORE_FAST              17 (profile_pic_url)
184         598 LOAD_CONST              33 ('\nð‡ð¢ð­ : ')

185         600 LOAD_GLOBAL              0 (hit)

184         612 FORMAT_VALUE             0
            614 LOAD_CONST              34 ('\nð†ð¦ðšð¢ð¥ : ')

186         616 LOAD_FAST                0 (email)

184         618 FORMAT_VALUE             0
            620 LOAD_CONST              35 ('\nð‘ðžð¬ðžð­: ')

187         622 LOAD_FAST                1 (res)

184         624 FORMAT_VALUE             0
            626 LOAD_CONST              36 ('\nð¢ð¬ð¦ð¢ : ')

188         628 LOAD_FAST               10 (full_name)

184         630 FORMAT_VALUE             0
            632 LOAD_CONST              37 ('\nð“ðšð¤ð¢ð©ðœ\u200cð¢:')

189         634 LOAD_FAST               11 (followers)

184         636 FORMAT_VALUE             0
            638 LOAD_CONST              38 ('\nð“ðšð¤ð¢ð© ðžðð¢ð¥ðžð§ : ')

190         640 LOAD_FAST               12 (following)

184         642 FORMAT_VALUE             0
            644 LOAD_CONST              39 ('\nðŠð®ð¥ð¥ðšð§Ä±ðœÄ± ð¢ð¬ð¦ð¢ : ')

191         646 LOAD_FAST                2 (username)

184         648 FORMAT_VALUE             0
            650 LOAD_CONST              40 ('\nðˆð : ')

192         652 LOAD_FAST                9 (Id)

184         654 FORMAT_VALUE             0
            656 LOAD_CONST              41 ('\nðŠð®ð«ð®ð¥ð®ð¦ : ')

193         658 LOAD_GLOBAL             15 (NULL + date)
            670 LOAD_FAST                9 (Id)
            672 PRECALL                  1
            676 CALL                     1

184         686 FORMAT_VALUE             0
            688 LOAD_CONST              42 ('\nð†ð¢ð³ð¥ð¢ð¦ð¢ : ')

194         690 LOAD_FAST               16 (is_private)

184         692 FORMAT_VALUE             0
            694 LOAD_CONST              43 ('\nðð¢ð¨ : ')

195         696 LOAD_FAST               14 (bio)

184         698 FORMAT_VALUE             0
            700 LOAD_CONST              44 ('\nâ€¹ âœ­ â€º ðµð‘Œ âŠ± @Rolexwhat\n        \n        ')
            702 BUILD_STRING            23
            704 STORE_FAST              18 (tlg)

199         706 LOAD_GLOBAL              7 (NULL + requests)            718 LOAD_ATTR                8 (post)
            728 LOAD_CONST              45 ('https://api.telegram.org/bot')
            730 LOAD_GLOBAL             18 (tok)
            742 FORMAT_VALUE             0
            744 LOAD_CONST              46 ('/sendMessage?chat_id=')
            746 LOAD_GLOBAL             20 (iid)
            758 FORMAT_VALUE             0
            760 LOAD_CONST              47 ('&text=')
            762 BUILD_STRING             5
            764 LOAD_GLOBAL             23 (NULL + str)
            776 LOAD_FAST               18 (tlg)
            778 PRECALL                  1
            782 CALL                     1
            792 BINARY_OP                0 (+)
            796 PRECALL                  1
            800 CALL                     1
            810 POP_TOP
            812 LOAD_CONST               0 (None)
            814 RETURN_VALUE
        >>  816 PUSH_EXC_INFO

201         818 LOAD_GLOBAL              6 (requests)
            830 LOAD_ATTR               12 (exceptions)
            840 LOAD_ATTR               13 (RequestException)
            850 CHECK_EXC_MATCH
            852 POP_JUMP_FORWARD_IF_FALSE    84 (to 1022)
            854 STORE_FAST              19 (e)

202         856 LOAD_CONST              33 ('\nð‡ð¢ð­ : ')

203         858 LOAD_GLOBAL              0 (hit)

202         870 FORMAT_VALUE             0
            872 LOAD_CONST              34 ('\nð†ð¦ðšð¢ð¥ : ')

204         874 LOAD_FAST                0 (email)

202         876 FORMAT_VALUE             0
            878 LOAD_CONST              48 ('\nð‘ðžð¬ðžð­ ')

205         880 LOAD_FAST                1 (res)

202         882 FORMAT_VALUE             0
            884 LOAD_CONST              49 ('\nð‹ð¢ð§ð¤ : https://www.instagram.com/')

206         886 LOAD_FAST                2 (username)

202         888 FORMAT_VALUE             0
            890 LOAD_CONST              50 ('?igsh=bXRmcXUyMXVxM3Mx\nâ€¹ âœ­ â€º ðµð‘Œ âŠ± @Rolexwhat\n        ')
            892 BUILD_STRING             9
            894 STORE_FAST              18 (tlg)

209         896 LOAD_GLOBAL              7 (NULL + requests)            908 LOAD_ATTR                8 (post)
            918 LOAD_CONST              45 ('https://api.telegram.org/bot')
            920 LOAD_GLOBAL             18 (tok)
            932 FORMAT_VALUE             0
            934 LOAD_CONST              46 ('/sendMessage?chat_id=')
            936 LOAD_GLOBAL             20 (iid)
            948 FORMAT_VALUE             0
            950 LOAD_CONST              47 ('&text=')
            952 BUILD_STRING             5
            954 LOAD_GLOBAL             23 (NULL + str)
            966 LOAD_FAST               18 (tlg)
            968 PRECALL                  1
            972 CALL                     1
            982 BINARY_OP                0 (+)
            986 PRECALL                  1
            990 CALL                     1
           1000 POP_TOP
           1002 POP_EXCEPT
           1004 LOAD_CONST               0 (None)
           1006 STORE_FAST              19 (e)
           1008 DELETE_FAST             19 (e)
           1010 LOAD_CONST               0 (None)
           1012 RETURN_VALUE
        >> 1014 LOAD_CONST               0 (None)
           1016 STORE_FAST              19 (e)
           1018 DELETE_FAST             19 (e)
           1020 RERAISE                  1

201     >> 1022 RERAISE                  0
        >> 1024 COPY                     3
           1026 POP_EXCEPT
           1028 RERAISE                  1
ExceptionTable:
  108 to 810 -> 816 [0]
  816 to 854 -> 1024 [1] lasti
  856 to 1000 -> 1014 [1] lasti
  1014 to 1022 -> 1024 [1] lasti

Disassembly of <code object gmail at 0x7df890d010, file "module", line 211>:
211           0 RESUME                   0

213           2 LOAD_CONST               1 ('')
              4 LOAD_METHOD              0 (join)
             26 LOAD_CONST               2 (<code object <genexpr> at 0x7c587c1b60, file "module", line 213>)
             28 MAKE_FUNCTION            0
             30 LOAD_GLOBAL              3 (NULL + range)
             42 LOAD_GLOBAL              5 (NULL + randrange)
             54 LOAD_CONST               3 (5)
             56 LOAD_CONST               4 (10)
             58 PRECALL                  2
             62 CALL                     2
             72 PRECALL                  1
             76 CALL                     1
             86 GET_ITER
             88 PRECALL                  0
             92 CALL                     0
            102 PRECALL                  1
            106 CALL                     1
            116 STORE_FAST               1 (name)

214         118 LOAD_GLOBAL              5 (NULL + randrange)
            130 LOAD_CONST               5 (1980)
            132 LOAD_CONST               6 (2010)
            134 PRECALL                  2
            138 CALL                     2
            148 LOAD_GLOBAL              5 (NULL + randrange)
            160 LOAD_CONST               7 (1)
            162 LOAD_CONST               8 (12)
            164 PRECALL                  2
            168 CALL                     2
            178 LOAD_GLOBAL              5 (NULL + randrange)
            190 LOAD_CONST               7 (1)
            192 LOAD_CONST               9 (28)
            194 PRECALL                  2
            198 CALL                     2
            208 BUILD_TUPLE              3
            210 STORE_FAST               2 (birthday)

215         212 LOAD_GLOBAL              7 (NULL + requests)            224 LOAD_ATTR                4 (Session)
            234 PRECALL                  0
            238 CALL                     0
            248 STORE_FAST               3 (s)

218         250 LOAD_CONST              10 ('text/html,application/xhtml+xml,application/xml;q=0.9,image/avif,image/webp,image/apng,*/*;q=0.8,application/signed-exchange;v=b3;q=0.7')

219         252 LOAD_CONST              11 ('en-US,en;q=0.9')

220         254 LOAD_CONST              12 ('https://accounts.google.com/')

221         256 LOAD_CONST              13 ('1')

222         258 LOAD_CONST              14 ('Mozilla/5.0 (Linux; Android 13; SM-G981B) AppleWebKit/537.36 (KHTML, like Gecko) Chrome/116.0.0.0 Mobile Safari/537.36')

223         260 LOAD_CONST              15 ('stable')

224         262 LOAD_CONST              16 ('Copyright 2024 Google LLC. All rights reserved.')

225         264 LOAD_CONST              17 ('2024')

217         266 LOAD_CONST              18 (('accept', 'accept-language', 'referer', 'upgrade-insecure-requests', 'user-agent', 'x-browser-channel', 'x-browser-copyright', 'x-browser-year'))
            268 BUILD_CONST_KEY_MAP      8
            270 STORE_FAST               4 (headers)

229         272 LOAD_CONST              19 ('false')

230         274 LOAD_CONST              20 ('https://mail.google.com/mail/u/0/')

231         276 LOAD_CONST              13 ('1')

232         278 LOAD_CONST              13 ('1')

233         280 LOAD_CONST              21 ('SignUp')

234         282 LOAD_CONST              22 ('GlifWebSignIn')
235         284 LOAD_CONST              20 ('https://mail.google.com/mail/u/0/')

236         286 LOAD_CONST              13 ('1')

237         288 LOAD_CONST              23 ('mail')

228         290 LOAD_CONST              24 (('biz', 'continue', 'ddm', 'emr', 'flowEntry', 'flowName', 'followup', 'osid', 'service'))
            292 BUILD_CONST_KEY_MAP      9
            294 STORE_FAST               5 (params)

240         296 LOAD_FAST                3 (s)
            298 LOAD_METHOD              5 (get)
            320 LOAD_CONST              25 ('https://accounts.google.com/lifecycle/flows/signup')
            322 LOAD_FAST                5 (params)
            324 LOAD_FAST                4 (headers)
            326 KW_NAMES                26
            328 PRECALL                  3
            332 CALL                     3
            342 STORE_FAST               6 (response)

241         344 LOAD_FAST                6 (response)
            346 LOAD_ATTR                6 (url)
            356 LOAD_METHOD              7 (split)
            378 LOAD_CONST              27 ('TL=')
            380 PRECALL                  1
            384 CALL                     1
            394 LOAD_CONST               7 (1)
            396 BINARY_SUBSCR
            406 STORE_FAST               7 (tl)

242         408 LOAD_FAST                6 (response)
            410 LOAD_ATTR                8 (text)
            420 LOAD_METHOD              7 (split)
            442 LOAD_CONST              28 ('"Qzxixc":"')
            444 PRECALL                  1
            448 CALL                     1
            458 LOAD_CONST               7 (1)
            460 BINARY_SUBSCR
            470 LOAD_METHOD              7 (split)
            492 LOAD_CONST              29 ('"')
            494 PRECALL                  1
            498 CALL                     1
            508 LOAD_CONST              30 (0)
            510 BINARY_SUBSCR
            520 STORE_FAST               8 (s1)

243         522 LOAD_FAST                6 (response)
            524 LOAD_ATTR                8 (text)
            534 LOAD_METHOD              7 (split)
            556 LOAD_CONST              31 ('"SNlM0e":"')
            558 PRECALL                  1
            562 CALL                     1
            572 LOAD_CONST               7 (1)
            574 BINARY_SUBSCR
            584 LOAD_METHOD              7 (split)
            606 LOAD_CONST              29 ('"')
            608 PRECALL                  1
            612 CALL                     1
            622 LOAD_CONST              30 (0)
            624 BINARY_SUBSCR
            634 STORE_FAST               9 (at)

245         636 LOAD_CONST              32 ('*/*')

246         638 LOAD_CONST              11 ('en-US,en;q=0.9')

247         640 LOAD_CONST              33 ('application/x-www-form-urlencoded;charset=UTF-8')

248         642 LOAD_CONST              34 ('https://accounts.google.com')

249         644 LOAD_CONST              12 ('https://accounts.google.com/')

250         646 LOAD_CONST              14 ('Mozilla/5.0 (Linux; Android 13; SM-G981B) AppleWebKit/537.36 (KHTML, like Gecko) Chrome/116.0.0.0 Mobile Safari/537.36')

251         648 LOAD_CONST              35 ('["GlifWebSignIn"]')

252         650 LOAD_CONST              36 ('["')
            652 LOAD_FAST                8 (s1)
            654 BINARY_OP                0 (+)
            658 LOAD_CONST              37 ('"]')
            660 BINARY_OP                0 (+)

253         664 LOAD_CONST              13 ('1')

244         666 LOAD_CONST              38 (('accept', 'accept-language', 'content-type', 'origin', 'referer', 'user-agent', 'x-goog-ext-278367001-jspb', 'x-goog-ext-391502476-jspb', 'x-same-domain'))
            668 BUILD_CONST_KEY_MAP      9
            670 STORE_FAST               4 (headers)

257         672 LOAD_CONST              39 ('E815hb')

258         674 LOAD_CONST              40 ('/lifecycle/steps/signup/name')

259         676 LOAD_CONST              41 ('en-US')

260         678 LOAD_FAST                7 (tl)

261         680 LOAD_CONST              42 ('c')

256         682 LOAD_CONST              43 (('rpcids', 'source-path', 'hl', 'TL', 'rt'))
            684 BUILD_CONST_KEY_MAP      5
            686 STORE_FAST               5 (params)

264         688 LOAD_CONST              44 ('f.req=%5B%5B%5B%22E815hb%22%2C%22%5B%5C%22{}%5C%22%2C%5C%22%5C%22%2Cnull%2Cnull%2Cnull%2C%5B%5D%2C%5B%5C%22https%3A%2F%2Fmail.google.com%2Fmail%2Fu%2F0%2F%5C%22%2C%5C%22mail%5C%22%5D%2C1%5D%22%2Cnull%2C%22generic%22%5D%5D%5D&at={}&')
            690 LOAD_METHOD              9 (format)
            712 LOAD_FAST                1 (name)
            714 LOAD_FAST                9 (at)
            716 PRECALL                  2
            720 CALL                     2
            730 STORE_FAST              10 (data)

266         732 LOAD_FAST                3 (s)
            734 LOAD_METHOD             10 (post)

267         756 LOAD_CONST              45 ('https://accounts.google.com/lifecycle/_/AccountLifecyclePlatformSignupUi/data/batchexecute')

268         758 LOAD_FAST                5 (params)

269         760 LOAD_FAST                4 (headers)

270         762 LOAD_FAST               10 (data)

266         764 KW_NAMES                46
            766 PRECALL                  4
            770 CALL                     4

271         780 LOAD_ATTR                8 (text)

266         790 STORE_FAST               6 (response)

276         792 LOAD_CONST              32 ('*/*')

277         794 LOAD_CONST              11 ('en-US,en;q=0.9')

278         796 LOAD_CONST              33 ('application/x-www-form-urlencoded;charset=UTF-8')

279         798 LOAD_CONST              34 ('https://accounts.google.com')

280         800 LOAD_CONST              12 ('https://accounts.google.com/')

281         802 LOAD_CONST              14 ('Mozilla/5.0 (Linux; Android 13; SM-G981B) AppleWebKit/537.36 (KHTML, like Gecko) Chrome/116.0.0.0 Mobile Safari/537.36')

282         804 LOAD_CONST              35 ('["GlifWebSignIn"]')

283         806 LOAD_CONST              36 ('["')
            808 LOAD_FAST                8 (s1)
            810 BINARY_OP                0 (+)
            814 LOAD_CONST              37 ('"]')
            816 BINARY_OP                0 (+)

284         820 LOAD_CONST              13 ('1')

275         822 LOAD_CONST              38 (('accept', 'accept-language', 'content-type', 'origin', 'referer', 'user-agent', 'x-goog-ext-278367001-jspb', 'x-goog-ext-391502476-jspb', 'x-same-domain'))
            824 BUILD_CONST_KEY_MAP      9
            826 STORE_FAST               4 (headers)

288         828 LOAD_CONST              47 ('eOY7Bb')

289         830 LOAD_CONST              48 ('/lifecycle/steps/signup/birthdaygender')

290         832 LOAD_CONST              41 ('en-US')

291         834 LOAD_FAST                7 (tl)

292         836 LOAD_CONST              42 ('c')

287         838 LOAD_CONST              43 (('rpcids', 'source-path', 'hl', 'TL', 'rt'))
            840 BUILD_CONST_KEY_MAP      5
            842 STORE_FAST               5 (params)

295         844 LOAD_CONST              49 ('f.req=%5B%5B%5B%22eOY7Bb%22%2C%22%5B%5B{}%2C{}%2C{}%5D%2C1%2Cnull%2Cnull%2Cnull%2C%5C%22%3Cf7Nqs-sCAAZfiOnPf4iN_32KOpLfQKL0ADQBEArZ1IBDTUyai2FYax3ViMI2wqBpWShhe-OPRhpMjnm9s14Yu65MknXEBWcyTyF3Jx0pzQAAAeGdAAAAC6cBB7EATZAxrowFF7vQ68oKqx7_sdcR_u8t8CJys-8G4opCIVySwUYaUnm-BovA8aThYLISPNMc8Pl3_B0GnkQJ_W4SIed6l6EcM7QLJ8AXVNAaVgbhsnD7q4lyQnlvR14HRW10oP85EU_bwG1E4QJH1V0KnVS4mIeoqB7zHOuxMuGifv6MB3GghUGTewh0tMN1jaf8yvX804tntlrlxm3OZgCZ2UxgDjUVOKFMv1Y3Txr16jJEJ56-T7qrPCtt6H1kmUvCIl_RDZzbt_sj5OLnbX1UvVA-VgG8-X9AJdvGhCKVhkf3iSkjy6_ZKsZSbsOsMjrm7ggnLdMStIf4AzbJIyMC7q4JMCaDaW_UI9SgquR8mHMpHGRmP7zY-WE47l7uRSpkI6oV93XJZ1zskJsxaDz7sDYHpzEL1RGPnkZU45XkIkwuc1ptU_AiM6SQyoZK7wFnhYxYfDQjSwaC7lOfngr6F2e4pDWkiC96QY4xLr6m2oUoDbyKR3ykccKEECEakFKzS-wSxIt9hK6nw-a9PEpVzhf6uIywZofNCs0KJOhhtv_ReG24DOC6NHX-FweCOkiYtT2sISrm6H8Wr4E89oU_mMWtpnXmhs8PB28SXw42-EdhRPsdcQkgKycOVT_IXwCc4Td9-t7715HP-L2XLk5i05aUrk-sHPPEz8SyL3odOb1SkwQ69bRQHfbPZr858iTDD0UaYWE_Jmb4wlGxYOSsvQ3EIljWDtj69cq3slKqMQu0ZC9bdqEh0p_T9zvsVwFiZThf19JL8PtqlXH5bgoEnPqdSfYbnJviQdUTAhuBPE-O8wgmdwl22wqkndacytncjwGR9cuXqAXUk_PbS-0fJGxIwI6-b7bhD7tS2DUAJk708UK5zFDLyqN6hFtj8AAjNM-XGIEqgTavCRhPnVT0u0l7p3iwtwKmRyAn42m3SwWhOQ6LDv-K2DyLl2OKfFu9Y-fPBh-2K2hIn2tKoGMgVbBR8AsVsYL7L6Bh5JIW7LCHaXNk3oDyHDx5QFaPtMmnIxcfFG90YSEPIgWV2nb67zDDacvvCkiPEQMXHJUcz1tuivaAgCTgW68wNYkUt89KJDhJTSWY2jcPsDIyCnS-SGESyR7mvbkvC3Robo0zVQm6q3Z73si9uqJiPmUGgBLycxUq2A_L3B-Hz35vBm5Oc5Hbe8hJToB03ilQzLa8Kld5BY8_kmmh6kfrOvi07uwfusHv3mKfijE2vaK3v2O2He41hCaOv3ExSfdPKb2V5nPPTw8ryyC5ZwlM_DLCU_k5xONsh4uplpRmydmJcit4aj5Ig0qLVF9MxIWU5xoDlvhKL9jHh-HVgIe-CPp4RMM5BfTxDgtESiF97RWjwrNeKn6Fc4311AdCrfZMcZ0F2JnQsfKAz4H-hoWbrOEVBkPcBt5umJ_iaCm0cQ2XTQMjzAtfWbRe6EGSxbkK-DXBl4EQM-6cnH1139MIHLzNou_Tltbl2HaomCS044CwhRNpe95KuYhM4Fz0Z_8rRjqy48tS_L4kQMX1CtxjBNfd4eUoaAIwAcz3LaL5BwL0DAYcV3xruTTuy6X8zFHe8fAIB9pJ_Pw0YJm3Ye28_tTg5xk0R4EU7_IPIHk6RrtSsG0Rfst3Qi5NRfWFg5h9LlmlHO_EUhdw1wbCICTqbS2A94aIBSCQzn7RmqOTTSIXwgFwnSBRKvoo0v9tKQ2rnMZsXRhzQgxwfmYOq29EUbuHmmWQjpRhfzX1Z6-5gXRPr4-PjrInsTiAi36xDyc8a1yTAhKMwnvf3GNqcK8lqx80VCASvcpYxGIAFl4QghroZbIJXlhccCWVF_xrzsw83QUdoZ5ExWi5f_cLvEXeZssdtan1orOaPJuWXT_0ryzpS9fOGtT68pL4HMAPLPpfwhiZ-wtZQU0oVy6T2L6oP1SIHQDU_QDaMR0MkStXNDj69r5cTDdYZiIbFkvWYeL1afTEljx1i2n2KKnDmpJfx2HeGCSZBMKZey24z_LDLA7MyJ2VBo4Zvmm23dwhWHOly56w9ul4sWzpHqgsqmKynRoaq9SXKrrmbR3f2GKBHSvy3Jm0Ln52zwIQfFSXpOjGXq5pkOXlvQc6MPuV3zADVmcUZs6ywI-ER3PkAaA-f-zG-ke_6jvOzGp6WF8UxnIk5tq3tus_R5pUjVQFjk6qZtWOP8VZd1TeJ54Oo_ywj8YAYCphkDtFYRMZSubmnI-F9LLlAfOiDwQ7r-iNvp8psduy9xrWdIpE_l23Y_qYJPHwvtopL3lB7juqEiFkhUts7NEugyWY-m6-9oEgsOY0lM4746V-XUxSeS7UkZkQZZM19g7GkWjJ61D98i0m2u_UYLnyDFQEaIxVhFcmS1Zq7OMsKm_gYpMt4LuD1F3N__Vj05QNyI59QNQADODveiHpfVva9Cd2AzBm9AKGwU4xDS_FyX3XRsRbfQFtqNzPf1LAERHlnHFn%5C%22%2C%5Bnull%2Cnull%2C%5C%22https%3A%2F%2Fmail.google.com%2Fmail%2Fu%2F0%2F%5C%22%2Cnull%2Cnull%2Cnull%2Cnull%2Cnull%2Cnull%2Cnull%2Cnull%2Cnull%2Cnull%2Cnull%2Cnull%2Cnull%2Cnull%2Cnull%2Cnull%2Cnull%2Cnull%2Cnull%2Cnull%2Cnull%2Cnull%2Cnull%2Cnull%2Cnull%2Cnull%2Cnull%2Cnull%2Cnull%2Cnull%2Cnull%2Cnull%2Cnull%2Cnull%2Cnull%2Cnull%2Cnull%2Cnull%2Cnull%2Cnull%2Cnull%2Cnull%2Cnull%2Cnull%2Cnull%2Cnull%2Cnull%2Cnull%2Cnull%2Cnull%2Cnull%2Cnull%2Cnull%2Cnull%2Cnull%2Cnull%2Cnull%2Cnull%2C%5C%22mail%5C%22%5D%5D%22%2Cnull%2C%22generic%22%5D%5D%5D&at={}&')
            846 LOAD_METHOD              9 (format)
            868 LOAD_FAST                2 (birthday)
            870 LOAD_CONST              30 (0)
            872 BINARY_SUBSCR
            882 LOAD_FAST                2 (birthday)
            884 LOAD_CONST               7 (1)
            886 BINARY_SUBSCR
            896 LOAD_FAST                2 (birthday)
            898 LOAD_CONST              50 (2)
            900 BINARY_SUBSCR
            910 LOAD_FAST                9 (at)
            912 PRECALL                  4
            916 CALL                     4
            926 STORE_FAST              10 (data)

297         928 LOAD_FAST                3 (s)
            930 LOAD_METHOD             10 (post)

298         952 LOAD_CONST              45 ('https://accounts.google.com/lifecycle/_/AccountLifecyclePlatformSignupUi/data/batchexecute')

299         954 LOAD_FAST                5 (params)

300         956 LOAD_FAST                4 (headers)

301         958 LOAD_FAST               10 (data)

297         960 KW_NAMES                46
            962 PRECALL                  4
            966 CALL                     4

302         976 LOAD_ATTR                8 (text)

297         986 STORE_FAST               6 (response)

307         988 LOAD_CONST              32 ('*/*')

308         990 LOAD_CONST              11 ('en-US,en;q=0.9')

309         992 LOAD_CONST              33 ('application/x-www-form-urlencoded;charset=UTF-8')

310         994 LOAD_CONST              34 ('https://accounts.google.com')

311         996 LOAD_CONST              12 ('https://accounts.google.com/')

312         998 LOAD_CONST              14 ('Mozilla/5.0 (Linux; Android 13; SM-G981B) AppleWebKit/537.36 (KHTML, like Gecko) Chrome/116.0.0.0 Mobile Safari/537.36')

313        1000 LOAD_CONST              35 ('["GlifWebSignIn"]')

314        1002 LOAD_CONST              36 ('["')
           1004 LOAD_FAST                8 (s1)
           1006 BINARY_OP                0 (+)
           1010 LOAD_CONST              37 ('"]')
           1012 BINARY_OP                0 (+)

315        1016 LOAD_CONST              13 ('1')

306        1018 LOAD_CONST              38 (('accept', 'accept-language', 'content-type', 'origin', 'referer', 'user-agent', 'x-goog-ext-278367001-jspb', 'x-goog-ext-391502476-jspb', 'x-same-domain'))
           1020 BUILD_CONST_KEY_MAP      9
           1022 STORE_FAST               4 (headers)

319        1024 LOAD_CONST              51 ('NHJMOd')

320        1026 LOAD_CONST              52 ('/lifecycle/steps/signup/username')

321        1028 LOAD_CONST              41 ('en-US')

322        1030 LOAD_FAST                7 (tl)

323        1032 LOAD_CONST              42 ('c')

318        1034 LOAD_CONST              43 (('rpcids', 'source-path', 'hl', 'TL', 'rt'))
           1036 BUILD_CONST_KEY_MAP      5
           1038 STORE_FAST               5 (params)

325        1040 LOAD_FAST                0 (email)
           1042 LOAD_METHOD              7 (split)
           1064 LOAD_CONST              53 ('@')
           1066 PRECALL                  1
           1070 CALL                     1
           1080 LOAD_CONST              30 (0)
           1082 BINARY_SUBSCR
           1092 STORE_FAST               0 (email)

327        1094 LOAD_CONST              54 ('f.req=%5B%5B%5B%22NHJMOd%22%2C%22%5B%5C%22{}%5C%22%2C0%2C0%2Cnull%2C%5Bnull%2Cnull%2Cnull%2Cnull%2C1%2C152855%5D%2C0%2C40%5D%22%2Cnull%2C%22generic%22%5D%5D%5D&at={}&')
           1096 LOAD_METHOD              9 (format)
           1118 LOAD_FAST                0 (email)
           1120 LOAD_FAST                9 (at)
           1122 PRECALL                  2
           1126 CALL                     2
           1136 STORE_FAST              10 (data)

329        1138 LOAD_FAST                3 (s)
           1140 LOAD_METHOD             10 (post)

330        1162 LOAD_CONST              45 ('https://accounts.google.com/lifecycle/_/AccountLifecyclePlatformSignupUi/data/batchexecute')

331        1164 LOAD_FAST                5 (params)

332        1166 LOAD_FAST                4 (headers)

333        1168 LOAD_FAST               10 (data)

329        1170 KW_NAMES                46
           1172 PRECALL                  4
           1176 CALL                     4

334        1186 LOAD_ATTR                8 (text)

329        1196 STORE_FAST               6 (response)

335        1198 LOAD_CONST              55 ('password')
           1200 LOAD_FAST                6 (response)
           1202 CONTAINS_OP              0
           1204 POP_JUMP_FORWARD_IF_FALSE   177 (to 1560)

336        1206 LOAD_GLOBAL             23 (NULL + info)
           1218 LOAD_FAST                0 (email)
           1220 PRECALL                  1
           1224 CALL                     1
           1234 POP_TOP

337        1236 LOAD_GLOBAL             24 (ge)
           1248 LOAD_CONST               7 (1)
           1250 BINARY_OP               13 (+=)
           1254 STORE_GLOBAL            12 (ge)

338        1256 LOAD_GLOBAL             26 (sys)
           1268 LOAD_ATTR               14 (stdout)
           1278 LOAD_METHOD             15 (write)
           1300 LOAD_CONST              56 ('\r')
           1302 LOAD_GLOBAL             32 (F)
           1314 FORMAT_VALUE             0
           1316 LOAD_CONST              57 ('Hit : ')
           1318 LOAD_GLOBAL             34 (M)
           1330 FORMAT_VALUE             0
           1332 LOAD_GLOBAL             24 (ge)
           1344 FORMAT_VALUE             0
           1346 LOAD_GLOBAL             36 (Z)
           1358 FORMAT_VALUE             0
           1360 LOAD_CONST              58 (' | KÃ¶tÃ¼ : ')
           1362 LOAD_GLOBAL             34 (M)
           1374 FORMAT_VALUE             0
           1376 LOAD_GLOBAL             38 (bi)
           1388 FORMAT_VALUE             0
           1390 LOAD_GLOBAL             40 (X)
           1402 FORMAT_VALUE             0
           1404 LOAD_CONST              59 (' | Ä°yi : ')
           1406 LOAD_GLOBAL             34 (M)
           1418 FORMAT_VALUE             0
           1420 LOAD_GLOBAL             42 (be)
           1432 FORMAT_VALUE             0
           1434 LOAD_GLOBAL             44 (C)
           1446 FORMAT_VALUE             0
           1448 LOAD_CONST              60 (' | Error : ')
           1450 LOAD_GLOBAL             34 (M)
           1462 FORMAT_VALUE             0
           1464 LOAD_GLOBAL             46 (gi)
           1476 FORMAT_VALUE             0
           1478 BUILD_STRING            17
           1480 PRECALL                  1
           1484 CALL                     1
           1494 LOAD_GLOBAL             26 (sys)
           1506 LOAD_ATTR               14 (stdout)
           1516 LOAD_METHOD             24 (flush)
           1538 PRECALL                  0
           1542 CALL                     0
           1552 BUILD_TUPLE              2
           1554 POP_TOP
           1556 LOAD_CONST               0 (None)
           1558 RETURN_VALUE

340     >> 1560 LOAD_GLOBAL             42 (be)
           1572 LOAD_CONST               7 (1)
           1574 BINARY_OP               13 (+=)
           1578 STORE_GLOBAL            21 (be)

341        1580 LOAD_GLOBAL             26 (sys)
           1592 LOAD_ATTR               14 (stdout)
           1602 LOAD_METHOD             15 (write)
           1624 LOAD_CONST              56 ('\r')
           1626 LOAD_GLOBAL             32 (F)
           1638 FORMAT_VALUE             0
           1640 LOAD_CONST              57 ('Hit : ')
           1642 LOAD_GLOBAL             34 (M)
           1654 FORMAT_VALUE             0
           1656 LOAD_GLOBAL             24 (ge)
           1668 FORMAT_VALUE             0
           1670 LOAD_GLOBAL             36 (Z)
           1682 FORMAT_VALUE             0
           1684 LOAD_CONST              58 (' | KÃ¶tÃ¼ : ')
           1686 LOAD_GLOBAL             34 (M)
           1698 FORMAT_VALUE             0
           1700 LOAD_GLOBAL             38 (bi)
           1712 FORMAT_VALUE             0
           1714 LOAD_GLOBAL             40 (X)
           1726 FORMAT_VALUE             0
           1728 LOAD_CONST              59 (' | Ä°yi : ')
           1730 LOAD_GLOBAL             34 (M)
           1742 FORMAT_VALUE             0
           1744 LOAD_GLOBAL             42 (be)
           1756 FORMAT_VALUE             0
           1758 LOAD_GLOBAL             44 (C)
           1770 FORMAT_VALUE             0
           1772 LOAD_CONST              60 (' | Error : ')
           1774 LOAD_GLOBAL             34 (M)
           1786 FORMAT_VALUE             0
           1788 LOAD_GLOBAL             46 (gi)
           1800 FORMAT_VALUE             0
           1802 BUILD_STRING            17
           1804 PRECALL                  1
           1808 CALL                     1
           1818 LOAD_GLOBAL             26 (sys)
           1830 LOAD_ATTR               14 (stdout)
           1840 LOAD_METHOD             24 (flush)
           1862 PRECALL                  0
           1866 CALL                     0
           1876 BUILD_TUPLE              2
           1878 POP_TOP
           1880 LOAD_CONST               0 (None)
           1882 RETURN_VALUE

Disassembly of <code object <genexpr> at 0x7c587c1b60, file "module", line 213>:
213           0 RETURN_GENERATOR
              2 POP_TOP
              4 RESUME                   0
              6 LOAD_FAST                0 (.0)
        >>    8 FOR_ITER                19 (to 48)
             10 STORE_FAST               1 (i)
             12 LOAD_GLOBAL              1 (NULL + choice)
             24 LOAD_CONST               0 ('abcdefghijklmnopqrstuvwxyz')
             26 PRECALL                  1
             30 CALL                     1
             40 YIELD_VALUE
             42 RESUME                   1
             44 POP_TOP
             46 JUMP_BACKWARD           20 (to 8)
        >>   48 LOAD_CONST               1 (None)
             50 RETURN_VALUE

Disassembly of <code object hott at 0x7de8915160, file "module", line 343>:
343           0 RESUME                   0

345           2 LOAD_GLOBAL              1 (NULL + requests)             14 LOAD_ATTR                1 (Session)
             24 PRECALL                  0
             28 CALL                     0
             38 STORE_FAST               1 (reqz)

346          40 LOAD_CONST               1 ('Mozilla/5.0 (Windows NT 6.1; WOW64) AppleWebKit/537.36 (KHTML, like Gecko) Chrome/42.0.2311.135 Safari/537.36')

347          42 LOAD_CONST               2 ('signup.live.com')

348          44 LOAD_CONST               3 ('keep-alive')

349          46 LOAD_CONST               4 ('XMLHttpRequest')

345          48 LOAD_CONST               5 (('User-Agent', 'Host', 'Connection', 'X-Requested-With'))
             50 BUILD_CONST_KEY_MAP      4
             52 STORE_FAST               2 (headers)

350          54 LOAD_CONST               6 ('https://signup.live.com/signup.aspx?lic=1')
             56 STORE_FAST               3 (url)
             58 LOAD_FAST                1 (reqz)
             60 LOAD_METHOD              2 (get)
             82 LOAD_FAST                3 (url)
             84 LOAD_FAST                2 (headers)
             86 KW_NAMES                 7
             88 PRECALL                  2
             92 CALL                     2
            102 STORE_FAST               4 (response)

351         104 LOAD_GLOBAL              7 (NULL + search)
            116 LOAD_CONST               8 ('apiCanary":"(.+?)",')
            118 LOAD_GLOBAL              9 (NULL + str)
            130 LOAD_FAST                4 (response)
            132 LOAD_ATTR                5 (content)
            142 PRECALL                  1
            146 CALL                     1
            156 PRECALL                  2
            160 CALL                     2
            170 LOAD_METHOD              6 (group)
            192 LOAD_CONST               9 (1)
            194 PRECALL                  1
            198 CALL                     1
            208 STORE_FAST               5 (apiCanary)

352         210 LOAD_GLOBAL              8 (str)
            222 LOAD_METHOD              7 (encode)
            244 LOAD_FAST                5 (apiCanary)
            246 PRECALL                  1
            250 CALL                     1
            260 LOAD_METHOD              8 (decode)
            282 LOAD_CONST              10 ('unicode_escape')
            284 PRECALL                  1
            288 CALL                     1
            298 LOAD_METHOD              7 (encode)
            320 LOAD_CONST              11 ('ascii')
            322 PRECALL                  1
            326 CALL                     1
            336 LOAD_METHOD              8 (decode)
            358 LOAD_CONST              10 ('unicode_escape')
            360 PRECALL                  1
            364 CALL                     1
            374 LOAD_METHOD              7 (encode)
            396 LOAD_CONST              11 ('ascii')
            398 PRECALL                  1
            402 CALL                     1
            412 LOAD_METHOD              8 (decode)
            434 LOAD_CONST              11 ('ascii')
            436 PRECALL                  1
            440 CALL                     1
            450 STORE_FAST               5 (apiCanary)
            452 LOAD_CONST              12 ('https://signup.live.com/API/CheckAvailableSigninNames')
            454 STORE_FAST               3 (url)

353         456 LOAD_FAST                0 (email)

354         458 LOAD_CONST              13 (True)

352         460 LOAD_CONST              14 (('signInName', 'includeSuggestions'))
            462 BUILD_CONST_KEY_MAP      2
            464 STORE_FAST               6 (json)

354         466 LOAD_FAST                1 (reqz)
            468 LOAD_METHOD              9 (post)
            490 LOAD_FAST                3 (url)

355         492 LOAD_CONST              15 ('application/x-www-form-urlencoded; charset=utf-8')

356         494 LOAD_FAST                5 (apiCanary)

354         496 LOAD_CONST              16 (('Content-Type', 'canary'))
            498 BUILD_CONST_KEY_MAP      2

357         500 LOAD_FAST                6 (json)

354         502 KW_NAMES                17
            504 PRECALL                  3
            508 CALL                     3
            518 STORE_FAST               7 (res)

358         520 LOAD_FAST                7 (res)
            522 LOAD_METHOD             10 (json)
            544 PRECALL                  0
            548 CALL                     0
            558 LOAD_CONST              18 ('isAvailable')
            560 BINARY_SUBSCR
            570 LOAD_CONST              13 (True)
            572 COMPARE_OP               2 (==)
            578 POP_JUMP_FORWARD_IF_FALSE   177 (to 934)

359         580 LOAD_GLOBAL             23 (NULL + info)
            592 LOAD_FAST                0 (email)
            594 PRECALL                  1
            598 CALL                     1
            608 POP_TOP
            610 LOAD_GLOBAL             24 (ge)
            622 LOAD_CONST               9 (1)
            624 BINARY_OP               13 (+=)
            628 STORE_GLOBAL            12 (ge)

360         630 LOAD_GLOBAL             26 (sys)
            642 LOAD_ATTR               14 (stdout)
            652 LOAD_METHOD             15 (write)
            674 LOAD_CONST              19 ('\r')
            676 LOAD_GLOBAL             32 (F)
            688 FORMAT_VALUE             0
            690 LOAD_CONST              20 ('Hit : ')
            692 LOAD_GLOBAL             34 (M)
            704 FORMAT_VALUE             0
            706 LOAD_GLOBAL             24 (ge)
            718 FORMAT_VALUE             0
            720 LOAD_GLOBAL             36 (Z)
            732 FORMAT_VALUE             0
            734 LOAD_CONST              21 (' | KÃ¶tÃ¼ : ')
            736 LOAD_GLOBAL             34 (M)
            748 FORMAT_VALUE             0
            750 LOAD_GLOBAL             38 (bi)
            762 FORMAT_VALUE             0
            764 LOAD_GLOBAL             40 (X)
            776 FORMAT_VALUE             0
            778 LOAD_CONST              22 (' | Ä°yi : ')
            780 LOAD_GLOBAL             34 (M)
            792 FORMAT_VALUE             0
            794 LOAD_GLOBAL             42 (be)
            806 FORMAT_VALUE             0
            808 LOAD_GLOBAL             44 (C)
            820 FORMAT_VALUE             0
            822 LOAD_CONST              23 (' | Error : ')
            824 LOAD_GLOBAL             34 (M)
            836 FORMAT_VALUE             0
            838 LOAD_GLOBAL             46 (gi)
            850 FORMAT_VALUE             0
            852 BUILD_STRING            17
            854 PRECALL                  1
            858 CALL                     1
            868 LOAD_GLOBAL             26 (sys)
            880 LOAD_ATTR               14 (stdout)
            890 LOAD_METHOD             24 (flush)
            912 PRECALL                  0
            916 CALL                     0
            926 BUILD_TUPLE              2
            928 POP_TOP
            930 LOAD_CONST               0 (None)
            932 RETURN_VALUE

362     >>  934 LOAD_GLOBAL             42 (be)
            946 LOAD_CONST               9 (1)
            948 BINARY_OP               13 (+=)
            952 STORE_GLOBAL            21 (be)

363         954 LOAD_GLOBAL             26 (sys)
            966 LOAD_ATTR               14 (stdout)
            976 LOAD_METHOD             15 (write)
            998 LOAD_CONST              19 ('\r')
           1000 LOAD_GLOBAL             32 (F)
           1012 FORMAT_VALUE             0
           1014 LOAD_CONST              20 ('Hit : ')
           1016 LOAD_GLOBAL             34 (M)
           1028 FORMAT_VALUE             0
           1030 LOAD_GLOBAL             24 (ge)
           1042 FORMAT_VALUE             0
           1044 LOAD_GLOBAL             36 (Z)
           1056 FORMAT_VALUE             0
           1058 LOAD_CONST              21 (' | KÃ¶tÃ¼ : ')
           1060 LOAD_GLOBAL             34 (M)
           1072 FORMAT_VALUE             0
           1074 LOAD_GLOBAL             38 (bi)
           1086 FORMAT_VALUE             0
           1088 LOAD_GLOBAL             40 (X)
           1100 FORMAT_VALUE             0
           1102 LOAD_CONST              22 (' | Ä°yi : ')
           1104 LOAD_GLOBAL             34 (M)
           1116 FORMAT_VALUE             0
           1118 LOAD_GLOBAL             42 (be)
           1130 FORMAT_VALUE             0
           1132 LOAD_GLOBAL             44 (C)
           1144 FORMAT_VALUE             0
           1146 LOAD_CONST              23 (' | Error : ')
           1148 LOAD_GLOBAL             34 (M)
           1160 FORMAT_VALUE             0
           1162 LOAD_GLOBAL             46 (gi)
           1174 FORMAT_VALUE             0
           1176 BUILD_STRING            17
           1178 PRECALL                  1
           1182 CALL                     1
           1192 LOAD_GLOBAL             26 (sys)
           1204 LOAD_ATTR               14 (stdout)
           1214 LOAD_METHOD             24 (flush)
           1236 PRECALL                  0
           1240 CALL                     0
           1250 BUILD_TUPLE              2
           1252 POP_TOP
           1254 LOAD_CONST               0 (None)
           1256 RETURN_VALUE

Disassembly of <code object insta2 at 0x7de891f8c0, file "module", line 364>:
364           0 RESUME                   0

366           2 BUILD_MAP                0

367           4 LOAD_CONST               1 ('X-Pigeon-Session-Id')
              6 LOAD_CONST               2 ('2b712457-ffad-4dba-9241-29ea2f472ac5')

366           8 MAP_ADD                  1

368          10 LOAD_CONST               3 ('X-Pigeon-Rawclienttime')
             12 LOAD_CONST               4 ('1707104597.347')

366          14 MAP_ADD                  1

369          16 LOAD_CONST               5 ('X-IG-Connection-Speed')
             18 LOAD_CONST               6 ('-1kbps')

366          20 MAP_ADD                  1

370          22 LOAD_CONST               7 ('X-IG-Bandwidth-Speed-KBPS')
             24 LOAD_CONST               8 ('-1.000')

366          26 MAP_ADD                  1

371          28 LOAD_CONST               9 ('X-IG-Bandwidth-TotalBytes-B')
             30 LOAD_CONST              10 ('0')

366          32 MAP_ADD                  1

372          34 LOAD_CONST              11 ('X-IG-Bandwidth-TotalTime-MS')
             36 LOAD_CONST              10 ('0')

366          38 MAP_ADD                  1

373          40 LOAD_CONST              12 ('X-IG-VP9-Capable')
             42 LOAD_CONST              13 ('false')

366          44 MAP_ADD                  1

374          46 LOAD_CONST              14 ('X-Bloks-Version-Id')
             48 LOAD_CONST              15 ('009f03b18280bb343b0862d663f31ac80c5fb30dfae9e273e43c63f13a9f31c0')

366          50 MAP_ADD                  1

375          52 LOAD_CONST              16 ('X-IG-Connection-Type')
             54 LOAD_CONST              17 ('WIFI')

366          56 MAP_ADD                  1

376          58 LOAD_CONST              18 ('X-IG-Capabilities')
             60 LOAD_CONST              19 ('3brTvw==')

366          62 MAP_ADD                  1

377          64 LOAD_CONST              20 ('X-IG-App-ID')
             66 LOAD_CONST              21 ('567067343352427')

366          68 MAP_ADD                  1

378          70 LOAD_CONST              22 ('User-Agent')
             72 LOAD_GLOBAL              1 (NULL + str)
             84 LOAD_GLOBAL              3 (NULL + generate_user_agent)
             96 PRECALL                  0
            100 CALL                     0
            110 PRECALL                  1
            114 CALL                     1

366         124 MAP_ADD                  1

379         126 LOAD_CONST              23 ('Accept-Language')
            128 LOAD_CONST              24 ('ar-IQ, en-US')

366         130 MAP_ADD                  1

380         132 LOAD_CONST              25 ('Cookie')
            134 LOAD_CONST              26 ('mid=Zbu4xQABAAE0k2Ok6rVxXpTD8PFQ; csrftoken=dG4dEIkWvAWpIj1B2M2mutWtdO1LiPCK')

366         136 MAP_ADD                  1

381         138 LOAD_CONST              27 ('Content-Type')
            140 LOAD_CONST              28 ('application/x-www-form-urlencoded; charset=UTF-8')

366         142 MAP_ADD                  1

382         144 LOAD_CONST              29 ('Accept-Encoding')
            146 LOAD_CONST              30 ('gzip, deflate')
366         148 MAP_ADD                  1

383         150 LOAD_CONST              31 ('Host')
            152 LOAD_CONST              32 ('i.instagram.com')

366         154 MAP_ADD                  1

384         156 LOAD_CONST              33 ('Liger')

385         158 LOAD_CONST              34 ('keep-alive')

386         160 LOAD_CONST              35 ('364')

366         162 LOAD_CONST              36 (('X-FB-HTTP-Engine', 'Connection', 'Content-Length'))
            164 BUILD_CONST_KEY_MAP      3
            166 DICT_UPDATE              1
            168 STORE_FAST               1 (headers)

389         170 LOAD_CONST              37 ('ef02f559b04e8d7cbe15fb8cf18e2b48fb686dafd056b7c9298c08f3e2007d43.{"_csrftoken":"dG4dEIkWvAWpIj1B2M2mutWtdO1LiPCK","adid":"5e7df201-a1ff-45ec-8107-31b10944e25c","guid":"b0382b46-1663-43a7-ba90-3949c43fd808","device_id":"android-71a5d65f74b8fcbc","query":"')
            172 LOAD_FAST                0 (email)
            174 FORMAT_VALUE             0
            176 LOAD_CONST              38 ('"}')
            178 BUILD_STRING             3

391         180 LOAD_CONST              39 ('4')

388         182 LOAD_CONST              40 (('signed_body', 'ig_sig_key_version'))
            184 BUILD_CONST_KEY_MAP      2
            186 STORE_FAST               2 (data)

393         188 NOP

394         190 LOAD_GLOBAL              5 (NULL + requests)            202 LOAD_ATTR                3 (post)
            212 LOAD_CONST              41 ('https://i.instagram.com/api/v1/accounts/send_recovery_flow_email/')
            214 LOAD_FAST                1 (headers)
            216 LOAD_FAST                2 (data)
            218 KW_NAMES                42
            220 PRECALL                  3
            224 CALL                     3
            234 LOAD_ATTR                4 (text)
            244 STORE_FAST               3 (re)
            246 JUMP_FORWARD            23 (to 294)
        >>  248 PUSH_EXC_INFO

395         250 LOAD_GLOBAL             10 (Exception)
            262 CHECK_EXC_MATCH
            264 POP_JUMP_FORWARD_IF_FALSE    10 (to 286)
            266 STORE_FAST               4 (e)
            268 POP_EXCEPT
            270 LOAD_CONST               0 (None)
            272 STORE_FAST               4 (e)
            274 DELETE_FAST              4 (e)
            276 JUMP_FORWARD             8 (to 294)
            278 LOAD_CONST               0 (None)
            280 STORE_FAST               4 (e)
            282 DELETE_FAST              4 (e)
            284 RERAISE                  1
        >>  286 RERAISE                  0
        >>  288 COPY                     3
            290 POP_EXCEPT
            292 RERAISE                  1

397     >>  294 LOAD_CONST              43 ('"can_recover_with_code"')
            296 LOAD_FAST                3 (re)
            298 CONTAINS_OP              0
            300 POP_JUMP_FORWARD_IF_FALSE   177 (to 656)

399         302 LOAD_GLOBAL             13 (NULL + hott)
            314 LOAD_FAST                0 (email)
            316 PRECALL                  1
            320 CALL                     1
            330 POP_TOP

400         332 LOAD_GLOBAL             14 (gi)
            344 LOAD_CONST              44 (1)
            346 BINARY_OP               13 (+=)
            350 STORE_GLOBAL             7 (gi)

401         352 LOAD_GLOBAL             16 (sys)
            364 LOAD_ATTR                9 (stdout)
            374 LOAD_METHOD             10 (write)
            396 LOAD_CONST              45 ('\r')
            398 LOAD_GLOBAL             22 (F)
            410 FORMAT_VALUE             0
            412 LOAD_CONST              46 ('Hit : ')
            414 LOAD_GLOBAL             24 (M)
            426 FORMAT_VALUE             0
            428 LOAD_GLOBAL             26 (ge)
            440 FORMAT_VALUE             0
            442 LOAD_GLOBAL             28 (Z)
            454 FORMAT_VALUE             0
            456 LOAD_CONST              47 (' | KÃ¶tÃ¼ : ')
            458 LOAD_GLOBAL             24 (M)
            470 FORMAT_VALUE             0
            472 LOAD_GLOBAL             30 (bi)
            484 FORMAT_VALUE             0
            486 LOAD_GLOBAL             32 (X)
            498 FORMAT_VALUE             0
            500 LOAD_CONST              48 (' | Ä°yi : ')
            502 LOAD_GLOBAL             24 (M)
            514 FORMAT_VALUE             0
            516 LOAD_GLOBAL             34 (be)
            528 FORMAT_VALUE             0
            530 LOAD_GLOBAL             36 (C)
            542 FORMAT_VALUE             0
            544 LOAD_CONST              49 (' | Error : ')
            546 LOAD_GLOBAL             24 (M)
            558 FORMAT_VALUE             0
            560 LOAD_GLOBAL             14 (gi)
            572 FORMAT_VALUE             0
            574 BUILD_STRING            17
            576 PRECALL                  1
            580 CALL                     1
            590 LOAD_GLOBAL             16 (sys)
            602 LOAD_ATTR                9 (stdout)
            612 LOAD_METHOD             19 (flush)
            634 PRECALL                  0
            638 CALL                     0
            648 BUILD_TUPLE              2
            650 POP_TOP
            652 LOAD_CONST               0 (None)
            654 RETURN_VALUE

402     >>  656 LOAD_CONST              50 ('"spam":true')
            658 LOAD_FAST                3 (re)
            660 CONTAINS_OP              0
            662 POP_JUMP_FORWARD_IF_FALSE    55 (to 774)

403         664 LOAD_GLOBAL             41 (NULL + os)
            676 LOAD_ATTR               21 (system)
            686 LOAD_GLOBAL             40 (os)
            698 LOAD_ATTR               22 (name)
            708 LOAD_CONST              51 ('nt')
            710 COMPARE_OP               2 (==)
            716 POP_JUMP_FORWARD_IF_FALSE     2 (to 722)
            718 LOAD_CONST              52 ('cls')
            720 JUMP_FORWARD             1 (to 724)
        >>  722 LOAD_CONST              53 ('clear')
        >>  724 PRECALL                  1
            728 CALL                     1
            738 POP_TOP

404         740 LOAD_GLOBAL             47 (NULL + print)
            752 LOAD_CONST              54 ('VPN AÃ‡ AMK : ')            754 PRECALL                  1
            758 CALL                     1
            768 POP_TOP
            770 LOAD_CONST               0 (None)
            772 RETURN_VALUE

406     >>  774 LOAD_GLOBAL             30 (bi)
            786 LOAD_CONST              44 (1)
            788 BINARY_OP               13 (+=)
            792 STORE_GLOBAL            15 (bi)

407         794 LOAD_GLOBAL             16 (sys)
            806 LOAD_ATTR                9 (stdout)
            816 LOAD_METHOD             10 (write)
            838 LOAD_CONST              45 ('\r')
            840 LOAD_GLOBAL             22 (F)
            852 FORMAT_VALUE             0
            854 LOAD_CONST              46 ('Hit : ')
            856 LOAD_GLOBAL             24 (M)
            868 FORMAT_VALUE             0
            870 LOAD_GLOBAL             26 (ge)
            882 FORMAT_VALUE             0
            884 LOAD_GLOBAL             28 (Z)
            896 FORMAT_VALUE             0
            898 LOAD_CONST              47 (' | KÃ¶tÃ¼ : ')
            900 LOAD_GLOBAL             24 (M)
            912 FORMAT_VALUE             0
            914 LOAD_GLOBAL             30 (bi)
            926 FORMAT_VALUE             0
            928 LOAD_GLOBAL             32 (X)
            940 FORMAT_VALUE             0
            942 LOAD_CONST              48 (' | Ä°yi : ')
            944 LOAD_GLOBAL             24 (M)
            956 FORMAT_VALUE             0
            958 LOAD_GLOBAL             34 (be)
            970 FORMAT_VALUE             0
            972 LOAD_GLOBAL             36 (C)
            984 FORMAT_VALUE             0
            986 LOAD_CONST              49 (' | Error : ')
            988 LOAD_GLOBAL             24 (M)
           1000 FORMAT_VALUE             0
           1002 LOAD_GLOBAL             14 (gi)
           1014 FORMAT_VALUE             0
           1016 BUILD_STRING            17
           1018 PRECALL                  1
           1022 CALL                     1
           1032 LOAD_GLOBAL             16 (sys)
           1044 LOAD_ATTR                9 (stdout)
           1054 LOAD_METHOD             19 (flush)
           1076 PRECALL                  0
           1080 CALL                     0
           1090 BUILD_TUPLE              2
           1092 POP_TOP
           1094 LOAD_CONST               0 (None)
           1096 RETURN_VALUE
ExceptionTable:
  190 to 244 -> 248 [0]
  248 to 266 -> 288 [1] lasti
  278 to 286 -> 288 [1] lasti

Disassembly of <code object insta at 0x7de891e570, file "module", line 408>:
408           0 RESUME                   0

410           2 BUILD_MAP                0

411           4 LOAD_CONST               1 ('X-Pigeon-Session-Id')
              6 LOAD_CONST               2 ('2b712457-ffad-4dba-9241-29ea2f472ac5')

410           8 MAP_ADD                  1

412          10 LOAD_CONST               3 ('X-Pigeon-Rawclienttime')
             12 LOAD_CONST               4 ('1707104597.347')

410          14 MAP_ADD                  1

413          16 LOAD_CONST               5 ('X-IG-Connection-Speed')
             18 LOAD_CONST               6 ('-1kbps')

410          20 MAP_ADD                  1

414          22 LOAD_CONST               7 ('X-IG-Bandwidth-Speed-KBPS')
             24 LOAD_CONST               8 ('-1.000')

410          26 MAP_ADD                  1

415          28 LOAD_CONST               9 ('X-IG-Bandwidth-TotalBytes-B')
             30 LOAD_CONST              10 ('0')

410          32 MAP_ADD                  1

416          34 LOAD_CONST              11 ('X-IG-Bandwidth-TotalTime-MS')
             36 LOAD_CONST              10 ('0')

410          38 MAP_ADD                  1

417          40 LOAD_CONST              12 ('X-IG-VP9-Capable')
             42 LOAD_CONST              13 ('false')

410          44 MAP_ADD                  1

418          46 LOAD_CONST              14 ('X-Bloks-Version-Id')
             48 LOAD_CONST              15 ('009f03b18280bb343b0862d663f31ac80c5fb30dfae9e273e43c63f13a9f31c0')

410          50 MAP_ADD                  1

419          52 LOAD_CONST              16 ('X-IG-Connection-Type')
             54 LOAD_CONST              17 ('WIFI')

410          56 MAP_ADD                  1

420          58 LOAD_CONST              18 ('X-IG-Capabilities')
             60 LOAD_CONST              19 ('3brTvw==')

410          62 MAP_ADD                  1

421          64 LOAD_CONST              20 ('X-IG-App-ID')
             66 LOAD_CONST              21 ('567067343352427')

410          68 MAP_ADD                  1

422          70 LOAD_CONST              22 ('User-Agent')
             72 LOAD_GLOBAL              1 (NULL + str)
             84 LOAD_GLOBAL              3 (NULL + generate_user_agent)
             96 PRECALL                  0
            100 CALL                     0
            110 PRECALL                  1
            114 CALL                     1

410         124 MAP_ADD                  1

423         126 LOAD_CONST              23 ('Accept-Language')
            128 LOAD_CONST              24 ('ar-IQ, en-US')

410         130 MAP_ADD                  1

424         132 LOAD_CONST              25 ('Cookie')
            134 LOAD_CONST              26 ('mid=Zbu4xQABAAE0k2Ok6rVxXpTD8PFQ; csrftoken=dG4dEIkWvAWpIj1B2M2mutWtdO1LiPCK')

410         136 MAP_ADD                  1

425         138 LOAD_CONST              27 ('Content-Type')
            140 LOAD_CONST              28 ('application/x-www-form-urlencoded; charset=UTF-8')

410         142 MAP_ADD                  1

426         144 LOAD_CONST              29 ('Accept-Encoding')
            146 LOAD_CONST              30 ('gzip, deflate')
410         148 MAP_ADD                  1

427         150 LOAD_CONST              31 ('Host')
            152 LOAD_CONST              32 ('i.instagram.com')

410         154 MAP_ADD                  1

428         156 LOAD_CONST              33 ('Liger')

429         158 LOAD_CONST              34 ('keep-alive')

430         160 LOAD_CONST              35 ('364')

410         162 LOAD_CONST              36 (('X-FB-HTTP-Engine', 'Connection', 'Content-Length'))
            164 BUILD_CONST_KEY_MAP      3
            166 DICT_UPDATE              1
            168 STORE_FAST               1 (headers)

433         170 LOAD_CONST              37 ('ef02f559b04e8d7cbe15fb8cf18e2b48fb686dafd056b7c9298c08f3e2007d43.{"_csrftoken":"dG4dEIkWvAWpIj1B2M2mutWtdO1LiPCK","adid":"5e7df201-a1ff-45ec-8107-31b10944e25c","guid":"b0382b46-1663-43a7-ba90-3949c43fd808","device_id":"android-71a5d65f74b8fcbc","query":"')
            172 LOAD_FAST                0 (email)
            174 FORMAT_VALUE             0
            176 LOAD_CONST              38 ('"}')
            178 BUILD_STRING             3

435         180 LOAD_CONST              39 ('4')

432         182 LOAD_CONST              40 (('signed_body', 'ig_sig_key_version'))
            184 BUILD_CONST_KEY_MAP      2
            186 STORE_FAST               2 (data)

437         188 NOP

438         190 LOAD_GLOBAL              5 (NULL + requests)            202 LOAD_ATTR                3 (post)
            212 LOAD_CONST              41 ('https://i.instagram.com/api/v1/accounts/send_recovery_flow_email/')
            214 LOAD_FAST                1 (headers)
            216 LOAD_FAST                2 (data)
            218 KW_NAMES                42
            220 PRECALL                  3
            224 CALL                     3
            234 LOAD_ATTR                4 (text)
            244 STORE_FAST               3 (re)
            246 JUMP_FORWARD            23 (to 294)
        >>  248 PUSH_EXC_INFO

439         250 LOAD_GLOBAL             10 (Exception)
            262 CHECK_EXC_MATCH
            264 POP_JUMP_FORWARD_IF_FALSE    10 (to 286)
            266 STORE_FAST               4 (e)
            268 POP_EXCEPT
            270 LOAD_CONST               0 (None)
            272 STORE_FAST               4 (e)
            274 DELETE_FAST              4 (e)
            276 JUMP_FORWARD             8 (to 294)
            278 LOAD_CONST               0 (None)
            280 STORE_FAST               4 (e)
            282 DELETE_FAST              4 (e)
            284 RERAISE                  1
        >>  286 RERAISE                  0
        >>  288 COPY                     3
            290 POP_EXCEPT
            292 RERAISE                  1

441     >>  294 LOAD_CONST              43 ('"can_recover_with_code"')
            296 LOAD_FAST                3 (re)
            298 CONTAINS_OP              0
            300 POP_JUMP_FORWARD_IF_FALSE   177 (to 656)

442         302 LOAD_GLOBAL             13 (NULL + gmail)
            314 LOAD_FAST                0 (email)
            316 PRECALL                  1
            320 CALL                     1
            330 POP_TOP

443         332 LOAD_GLOBAL             14 (gi)
            344 LOAD_CONST              44 (1)
            346 BINARY_OP               13 (+=)
            350 STORE_GLOBAL             7 (gi)

444         352 LOAD_GLOBAL             16 (sys)
            364 LOAD_ATTR                9 (stdout)
            374 LOAD_METHOD             10 (write)
            396 LOAD_CONST              45 ('\r')
            398 LOAD_GLOBAL             22 (F)
            410 FORMAT_VALUE             0
            412 LOAD_CONST              46 ('Hit : ')
            414 LOAD_GLOBAL             24 (M)
            426 FORMAT_VALUE             0
            428 LOAD_GLOBAL             26 (ge)
            440 FORMAT_VALUE             0
            442 LOAD_GLOBAL             28 (Z)
            454 FORMAT_VALUE             0
            456 LOAD_CONST              47 (' | KÃ¶tÃ¼ : ')
            458 LOAD_GLOBAL             24 (M)
            470 FORMAT_VALUE             0
            472 LOAD_GLOBAL             30 (bi)
            484 FORMAT_VALUE             0
            486 LOAD_GLOBAL             32 (X)
            498 FORMAT_VALUE             0
            500 LOAD_CONST              48 (' | Ä°yi : ')
            502 LOAD_GLOBAL             24 (M)
            514 FORMAT_VALUE             0
            516 LOAD_GLOBAL             34 (be)
            528 FORMAT_VALUE             0
            530 LOAD_GLOBAL             36 (C)
            542 FORMAT_VALUE             0
            544 LOAD_CONST              49 (' | Error: ')
            546 LOAD_GLOBAL             24 (M)
            558 FORMAT_VALUE             0
            560 LOAD_GLOBAL             14 (gi)
            572 FORMAT_VALUE             0
            574 BUILD_STRING            17
            576 PRECALL                  1
            580 CALL                     1
            590 LOAD_GLOBAL             16 (sys)
            602 LOAD_ATTR                9 (stdout)
            612 LOAD_METHOD             19 (flush)
            634 PRECALL                  0
            638 CALL                     0
            648 BUILD_TUPLE              2
            650 POP_TOP
            652 LOAD_CONST               0 (None)
            654 RETURN_VALUE

445     >>  656 LOAD_CONST              50 ('"spam":true')
            658 LOAD_FAST                3 (re)
            660 CONTAINS_OP              0
            662 POP_JUMP_FORWARD_IF_FALSE    55 (to 774)

446         664 LOAD_GLOBAL             41 (NULL + os)
            676 LOAD_ATTR               21 (system)
            686 LOAD_GLOBAL             40 (os)
            698 LOAD_ATTR               22 (name)
            708 LOAD_CONST              51 ('nt')
            710 COMPARE_OP               2 (==)
            716 POP_JUMP_FORWARD_IF_FALSE     2 (to 722)
            718 LOAD_CONST              52 ('cls')
            720 JUMP_FORWARD             1 (to 724)
        >>  722 LOAD_CONST              53 ('clear')
        >>  724 PRECALL                  1
            728 CALL                     1
            738 POP_TOP

447         740 LOAD_GLOBAL             47 (NULL + print)
            752 LOAD_CONST              54 ('VPN AÃ‡ AMK : ')            754 PRECALL                  1
            758 CALL                     1
            768 POP_TOP
            770 LOAD_CONST               0 (None)
            772 RETURN_VALUE

449     >>  774 LOAD_GLOBAL             30 (bi)
            786 LOAD_CONST              44 (1)
            788 BINARY_OP               13 (+=)
            792 STORE_GLOBAL            15 (bi)

450         794 LOAD_GLOBAL             16 (sys)
            806 LOAD_ATTR                9 (stdout)
            816 LOAD_METHOD             10 (write)
            838 LOAD_CONST              45 ('\r')
            840 LOAD_GLOBAL             22 (F)
            852 FORMAT_VALUE             0
            854 LOAD_CONST              46 ('Hit : ')
            856 LOAD_GLOBAL             24 (M)
            868 FORMAT_VALUE             0
            870 LOAD_GLOBAL             26 (ge)
            882 FORMAT_VALUE             0
            884 LOAD_GLOBAL             28 (Z)
            896 FORMAT_VALUE             0
            898 LOAD_CONST              47 (' | KÃ¶tÃ¼ : ')
            900 LOAD_GLOBAL             24 (M)
            912 FORMAT_VALUE             0
            914 LOAD_GLOBAL             30 (bi)
            926 FORMAT_VALUE             0
            928 LOAD_GLOBAL             32 (X)
            940 FORMAT_VALUE             0
            942 LOAD_CONST              48 (' | Ä°yi : ')
            944 LOAD_GLOBAL             24 (M)
            956 FORMAT_VALUE             0
            958 LOAD_GLOBAL             34 (be)
            970 FORMAT_VALUE             0
            972 LOAD_GLOBAL             36 (C)
            984 FORMAT_VALUE             0
            986 LOAD_CONST              49 (' | Error: ')
            988 LOAD_GLOBAL             24 (M)
           1000 FORMAT_VALUE             0
           1002 LOAD_GLOBAL             14 (gi)
           1014 FORMAT_VALUE             0
           1016 BUILD_STRING            17
           1018 PRECALL                  1
           1022 CALL                     1
           1032 LOAD_GLOBAL             16 (sys)
           1044 LOAD_ATTR                9 (stdout)
           1054 LOAD_METHOD             19 (flush)
           1076 PRECALL                  0
           1080 CALL                     0
           1090 BUILD_TUPLE              2
           1092 POP_TOP
           1094 LOAD_CONST               0 (None)
           1096 RETURN_VALUE
ExceptionTable:
  190 to 244 -> 248 [0]
  248 to 266 -> 288 [1] lasti
  278 to 286 -> 288 [1] lasti

Disassembly of <code object random1 at 0x7dd892dbb0, file "module", line 451>:
              0 MAKE_CELL                8 (g)

451           2 RESUME                   0

452     >>    4 NOP

453     >>    6 LOAD_GLOBAL              1 (NULL + random)
             18 LOAD_ATTR                1 (choice)

454          28 BUILD_LIST               0
             30 LOAD_CONST               2 (('azertyuiopmlkjhgfdsqwxcvbn', 'azertyuiopmlkjhgfdsqwxcvbn', 'azertyuiopmlkjhgfdsqwxcvbn', 'azertyuiopmlkjhgfdsqwxcvbn', 'azertyuiopmlkjhgfdsqwxcvbn', 'abcdefghijklmnopqrstuvwxyzÃ©Ã¨ÃªÃ«Ã Ã¢Ã¤Ã´Ã¹Ã»Ã¼Ã®Ã¯Ã§', 'abcdefghijklmnopqrstuvwxyzÃ©Ã¨ÃªÃ«Ã Ã¢Ã¤Ã´Ã¹Ã»Ã¼Ã®Ã¯Ã§', 'abcdefghijklmnopqrstuvwxyzÃ©Ã¨ÃªÃ«Ã Ã¢Ã¤Ã´Ã¹Ã»Ã¼Ã®Ã¯Ã§', 'abcdefghijklmnopqrstuvwxyzÃ©Ã¨ÃªÃ«Ã Ã¢Ã¤Ã´Ã¹Ã»Ã¼Ã®Ã¯Ã§', 'abcdefghijklmnopqrstuvwxyzÃ±', 'abcdefghijklmnopqrstuvwxyzÃ±', 'abcdefghijklmnopqrstuvwxyzÃ±', 'Ð°Ð±Ð²Ð³Ð´ÐµÑ‘Ð¶Ð·Ð¸Ð¹ÐºÐ»Ð¼Ð½Ð¾Ð¿Ñ€ÑÑ‚ÑƒÑ„Ñ…Ñ†Ñ‡ÑˆÑ‰ÑŠÑ‹ÑŒÑÑŽÑ', 'Ð°Ð±Ð²Ð³Ð´ÐµÑ‘Ð¶Ð·Ð¸Ð¹ÐºÐ»Ð¼Ð½Ð¾Ð¿Ñ€ÑÑ‚ÑƒÑ„Ñ…Ñ†Ñ‡ÑˆÑ‰ÑŠÑ‹ÑŒÑÑŽÑ', 'Ð°Ð±Ð²Ð³Ð´ÐµÑ‘Ð¶Ð·Ð¸Ð¹ÐºÐ»Ð¼Ð½Ð¾Ð¿Ñ€ÑÑ‚ÑƒÑ„Ñ…Ñ†Ñ‡ÑˆÑ‰ÑŠÑ‹ÑŒÑÑŽÑ', 'çš„ä¸€æ˜¯ä¸äº†äººæˆ‘åœ¨æœ‰ä»–è¿™ä¸ºä¹‹å¤§æ¥ä»¥ä¸ªä¸­ä¸Šä»¬åˆ°è¯´æ—¶å›½å’Œåœ°è¦å°±å‡ºä¼šå¯ä¹Ÿä½ å¯¹ç”Ÿèƒ½è€Œå­é‚£å¾—äºŽç€ä¸‹è‡ªä¹‹', 'çš„ä¸€æ˜¯ä¸äº†äººæˆ‘åœ¨æœ‰ä»–è¿™ä¸ºä¹‹å¤§æ¥ä»¥ä¸ªä¸­ä¸Šä»¬åˆ°è¯´æ—¶å›½å’Œåœ°è¦å°±å‡ºä¼šå¯ä¹Ÿä½ å¯¹ç”Ÿèƒ½è€Œå­é‚£å¾—äºŽç€ä¸‹è‡ªä¹‹', 'çš„ä¸€æ˜¯ä¸äº†äººæˆ‘åœ¨æœ‰ä»–è¿™ä¸ºä¹‹å¤§æ¥ä»¥ä¸ªä¸­ä¸Šä»¬åˆ°è¯´æ—¶å›½å’Œåœ°è¦å°±å‡ºä¼šå¯ä¹Ÿä½ å¯¹ç”Ÿèƒ½è€Œå­é‚£å¾—äºŽç€ä¸‹è‡ªä¹‹', 'ã‚¢ã‚¤ã‚¦ã‚¨ã‚ªã‚«ã‚­ã‚¯ã‚±ã‚³ã‚µã‚·ã‚¹ã‚»ã‚½ã‚¿ãƒãƒ„ãƒ†ãƒˆãƒŠãƒ‹ãƒŒãƒãƒŽãƒãƒ’ãƒ•ãƒ˜ãƒ›ãƒžãƒŸãƒ ãƒ¡ãƒ¢ãƒ¤ãƒ¦ãƒ¨ãƒ©ãƒªãƒ«ãƒ¬ãƒ­ãƒ¯ãƒ²ãƒ³', 'ã‚¢ã‚¤ã‚¦ã‚¨ã‚ªã‚«ã‚­ã‚¯ã‚±ã‚³ã‚µã‚·ã‚¹ã‚»ã‚½ã‚¿ãƒãƒ„ãƒ†ãƒˆãƒŠãƒ‹ãƒŒãƒãƒŽãƒãƒ’ãƒ•ãƒ˜ãƒ›ãƒžãƒŸãƒ ãƒ¡ãƒ¢ãƒ¤ãƒ¦ãƒ¨ãƒ©ãƒªãƒ«ãƒ¬ãƒ­ãƒ¯ãƒ²ãƒ³', 'ã‚ã„ã†ãˆãŠã‹ããã‘ã“ã•ã—ã™ã›ããŸã¡ã¤ã¦ã¨ãªã«ã¬ã­ã®ã¯ã²ãµã¸ã»ã¾ã¿ã‚€ã‚ã‚‚ã‚„ã‚†ã‚ˆã‚‰ã‚Šã‚‹ã‚Œã‚ã‚ã‚’ã‚“', 'ã‚ã„ã†ãˆãŠã‹ããã‘ã“ã•ã—ã™ã›ããŸã¡ã¤ã¦ã¨ãªã«ã¬ã­ã®ã¯ã²ãµã¸ã»ã¾ã¿ã‚€ã‚ã‚‚ã‚„ã‚†ã‚ˆã‚‰ã‚Šã‚‹ã‚Œã‚ã‚ã‚’ã‚“', '××‘×’×“×”×•×–×—×˜×™×›×œ×ž× ×¡×¢×¤×¦×§×¨×©×ª', '××‘×’×“×”×•×–×—×˜×™×›×œ×ž× ×¡×¢×¤×¦×§×¨×©×ª', 'Î±Î²Î³Î´ÎµÎ¶Î·Î¸Î¹ÎºÎ»Î¼Î½Î¾Î¿Ï€ÏÏƒÏ„Ï…Ï†Ï‡ÏˆÏ‰', 'Î±Î²Î³Î´ÎµÎ¶Î·Î¸Î¹ÎºÎ»Î¼Î½Î¾Î¿Ï€ÏÏƒÏ„Ï…Ï†Ï‡ÏˆÏ‰', 'abcdefghijklmnopqrstuvwxyzÃ§', 'abcdefghijklmnopqrstuvwxyzÃ§', 'à¸à¸‚à¸ƒà¸„à¸…à¸†à¸‡à¸ˆà¸‰à¸Šà¸‹à¸Œà¸à¸Žà¸à¸à¸‘à¸’à¸“à¸”à¸•à¸–à¸—à¸˜à¸™à¸šà¸›à¸œà¸à¸žà¸Ÿà¸ à¸¡à¸¢à¸£à¸¤à¸¤à¸¥à¸¦à¸§à¸¨à¸©à¸ªà¸«à¸¬à¸­à¸®', 'à¸à¸‚à¸ƒà¸„à¸…à¸†à¸‡à¸ˆà¸‰à¸Šà¸‹à¸Œà¸à¸Žà¸à¸à¸‘à¸’à¸“à¸”à¸•à¸–à¸—à¸˜à¸™à¸šà¸›à¸œà¸à¸žà¸Ÿà¸ à¸¡à¸¢à¸£à¸¤à¸¤à¸¥à¸¦à¸§à¸¨à¸©à¸ªà¸«à¸¬à¸­à¸®', 'à¤…à¤†à¤‡à¤ˆà¤‰à¤Šà¤‹à¤à¤à¤“à¤”à¤…à¤‚à¤…à¤ƒà¤•à¤–à¤—à¤˜à¤™à¤šà¤›à¤œà¤à¤žà¤Ÿà¤ à¤¡à¤¢à¤£à¤¤à¤¥à¤¦à¤§à¤¨à¤ªà¤«à¤¬à¤­à¤®à¤¯à¤°à¤²à¤µà¤¶à¤·à¤¸à¤¹à¤•à¥à¤·à¤¤à¥à¤°à¤œà¥à¤ž', 'à¤…à¤†à¤‡à¤ˆà¤‰à¤Šà¤‹à¤à¤à¤“à¤”à¤…à¤‚à¤…à¤ƒà¤•à¤–à¤—à¤˜à¤™à¤šà¤›à¤œà¤à¤žà¤Ÿà¤ à¤¡à¤¢à¤£à¤¤à¤¥à¤¦à¤§à¤¨à¤ªà¤«à¤¬à¤­à¤®à¤¯à¤°à¤²à¤µà¤¶à¤·à¤¸à¤¹à¤•à¥ à¤·à¤¤à¥à¤°à¤œà¥à¤ž'))
             32 LIST_EXTEND              1

453          34 PRECALL                  1
             38 CALL                     1
             48 STORE_DEREF              8 (g)

490          50 LOAD_CONST               3 ('')
             52 LOAD_METHOD              2 (join)
             74 LOAD_CLOSURE             8 (g)
             76 BUILD_TUPLE              1
             78 LOAD_CONST               4 (<code object <genexpr> at 0x7c58772130, file "module", line 490>)
             80 MAKE_FUNCTION            8 (closure)
             82 LOAD_GLOBAL              7 (NULL + range)
             94 LOAD_GLOBAL              1 (NULL + random)
            106 LOAD_ATTR                4 (randrange)
            116 LOAD_CONST               5 (4)
            118 LOAD_CONST               6 (9)
            120 PRECALL                  2
            124 CALL                     2
            134 PRECALL                  1
            138 CALL                     1
            148 GET_ITER
            150 PRECALL                  0
            154 CALL                     0
            164 PRECALL                  1
            168 CALL                     1
            178 STORE_FAST               0 (keyword)

492         180 LOAD_CONST               7 ('rur')
            182 LOAD_CONST               8 ('"LDC\\05467838469205\\0541758153066:01f72be7578ed09a57bfe3e41c19af58848e0e965e0549f6d1f5a0168a652d2bfa28cd9a"')

491         184 BUILD_MAP                1
            186 STORE_FAST               1 (cookies)

495         188 BUILD_MAP                0

496         190 LOAD_CONST               9 ('accept')
            192 LOAD_CONST              10 ('*/*')

495         194 MAP_ADD                  1

497         196 LOAD_CONST              11 ('accept-language')
            198 LOAD_CONST              12 ('ar,en-US;q=0.9,en;q=0.8')

495         200 MAP_ADD                  1

498         202 LOAD_CONST              13 ('content-type')
            204 LOAD_CONST              14 ('application/x-www-form-urlencoded')

495         206 MAP_ADD                  1

500         208 LOAD_CONST              15 ('origin')
            210 LOAD_CONST              16 ('https://www.instagram.com')

495         212 MAP_ADD                  1

501         214 LOAD_CONST              17 ('priority')
            216 LOAD_CONST              18 ('u=1, i')

495         218 MAP_ADD                  1

502         220 LOAD_CONST              19 ('referer')
            222 LOAD_CONST              20 ('https://www.instagram.com/')

495         224 MAP_ADD                  1

503         226 LOAD_CONST              21 ('sec-ch-prefers-color-scheme')
            228 LOAD_CONST              22 ('light')

495         230 MAP_ADD                  1

504         232 LOAD_CONST              23 ('sec-ch-ua')
            234 LOAD_CONST              24 ('"Chromium";v="128", "Not;A=Brand";v="24", "Google Chrome";v="128"')

495         236 MAP_ADD                  1

505         238 LOAD_CONST              25 ('sec-ch-ua-full-version-list')
            240 LOAD_CONST              26 ('"Chromium";v="128.0.6613.138", "Not;A=Brand";v="24.0.0.0", "Google Chrome";v="128.0.6613.138"')

495         242 MAP_ADD                  1

506         244 LOAD_CONST              27 ('sec-ch-ua-mobile')
            246 LOAD_CONST              28 ('?0')

495         248 MAP_ADD                  1

507         250 LOAD_CONST              29 ('sec-ch-ua-model')
            252 LOAD_CONST              30 ('""')

495         254 MAP_ADD                  1

508         256 LOAD_CONST              31 ('sec-ch-ua-platform')
            258 LOAD_CONST              32 ('"Windows"')

495         260 MAP_ADD                  1

509         262 LOAD_CONST              33 ('sec-ch-ua-platform-version')
            264 LOAD_CONST              34 ('"15.0.0"')

495         266 MAP_ADD                  1

510         268 LOAD_CONST              35 ('sec-fetch-dest')
            270 LOAD_CONST              36 ('empty')

495         272 MAP_ADD                  1

511         274 LOAD_CONST              37 ('sec-fetch-mode')
            276 LOAD_CONST              38 ('cors')

495         278 MAP_ADD                  1

512         280 LOAD_CONST              39 ('sec-fetch-site')
            282 LOAD_CONST              40 ('same-origin')

495         284 MAP_ADD                  1

513         286 LOAD_CONST              41 ('user-agent')
            288 LOAD_GLOBAL             11 (NULL + str)
            300 LOAD_GLOBAL             13 (NULL + generate_user_agent)
            312 PRECALL                  0
            316 CALL                     0
            326 PRECALL                  1
            330 CALL                     1

495         340 MAP_ADD                  1

514         342 LOAD_CONST              42 ('129477')

515         344 LOAD_CONST              43 ('235c9483d007713b45fc75b34c76332d68d579a4300a1db1da94670c3a05089f')

516         346 LOAD_CONST              44 ('mf3zd6qWxnKgh9BaNRI5Ldpms2NrH62X')

517         348 LOAD_CONST              45 ('PolarisSearchBoxRefetchableQuery')

518         350 LOAD_CONST              46 ('BslibIYRWxn19hyIaPyrZV')

519         352 LOAD_CONST              47 ('936619743392459')

495         354 LOAD_CONST              48 (('x-asbd-id', 'x-bloks-version-id', 'x-csrftoken', 'x-fb-friendly-name', 'x-fb-lsd', 'x-ig-app-id'))
            356 BUILD_CONST_KEY_MAP      6
            358 DICT_UPDATE              1
            360 STORE_FAST               2 (headers)

523         362 LOAD_CONST              49 ('{"data":{"context":"blended","include_reel":"true","query":"')
            364 LOAD_FAST                0 (keyword)
            366 BINARY_OP                0 (+)
            370 LOAD_CONST              50 ('","rank_token":"","search_surface":"web_top_search"},"hasQuery":true}')
            372 BINARY_OP                0 (+)

524         376 LOAD_CONST              51 ('7935512656557707')

522         378 LOAD_CONST              52 (('variables', 'doc_id'))
            380 BUILD_CONST_KEY_MAP      2
            382 STORE_FAST               3 (data)

526         384 NOP

528         386 LOAD_GLOBAL             15 (NULL + requests)            398 LOAD_ATTR                8 (post)
            408 LOAD_CONST              53 ('https://www.instagram.com/graphql/query')
            410 LOAD_FAST                1 (cookies)
            412 LOAD_FAST                2 (headers)
            414 LOAD_FAST                3 (data)
            416 KW_NAMES                54
            418 PRECALL                  4
            422 CALL                     4
            432 LOAD_METHOD              9 (json)
            454 PRECALL                  0
            458 CALL                     0
            468 LOAD_CONST              55 ('data')
            470 BINARY_SUBSCR
            480 LOAD_CONST              56 ('xdt_api__v1__fbsearch__topsearch_connection')
            482 BINARY_SUBSCR
            492 LOAD_CONST              57 ('users')
            494 BINARY_SUBSCR
            504 STORE_FAST               4 (response)

529         506 LOAD_FAST                4 (response)
            508 GET_ITER
        >>  510 FOR_ITER                36 (to 584)
            512 STORE_FAST               5 (Hus)

530         514 LOAD_FAST                5 (Hus)
            516 LOAD_CONST              58 ('user')
            518 BINARY_SUBSCR
            528 LOAD_CONST              59 ('username')
            530 BINARY_SUBSCR
            540 STORE_FAST               6 (d_7vw)

531         542 LOAD_FAST                6 (d_7vw)
            544 LOAD_CONST              60 ('@gmail.com')
            546 BINARY_OP                0 (+)
            550 STORE_FAST               7 (email)

532         552 LOAD_GLOBAL             21 (NULL + insta)
            564 LOAD_FAST                7 (email)
            566 PRECALL                  1
            570 CALL                     1
            580 POP_TOP
            582 JUMP_BACKWARD           37 (to 510)

529     >>  584 JUMP_FORWARD             8 (to 602)
        >>  586 PUSH_EXC_INFO

533         588 POP_TOP

534         590 POP_EXCEPT
            592 EXTENDED_ARG             1
            594 JUMP_BACKWARD          296 (to 4)
        >>  596 COPY                     3
            598 POP_EXCEPT
            600 RERAISE                  1

452     >>  602 EXTENDED_ARG             1
            604 JUMP_BACKWARD          300 (to 6)
ExceptionTable:
  386 to 582 -> 586 [0]
  586 to 588 -> 596 [1] lasti

Disassembly of <code object <genexpr> at 0x7c58772130, file "module", line 490>:
              0 COPY_FREE_VARS           1

490           2 RETURN_GENERATOR
              4 POP_TOP
              6 RESUME                   0
              8 LOAD_FAST                0 (.0)
        >>   10 FOR_ITER                24 (to 60)
             12 STORE_FAST               1 (i)
             14 LOAD_GLOBAL              1 (NULL + random)
             26 LOAD_ATTR                1 (choice)
             36 LOAD_DEREF               2 (g)
             38 PRECALL                  1
             42 CALL                     1
             52 YIELD_VALUE
             54 RESUME                   1
             56 POP_TOP
             58 JUMP_BACKWARD           25 (to 10)
        >>   60 LOAD_CONST               0 (None)
             62 RETURN_VALUE

Disassembly of <code object ee at 0x7dc892b9d0, file "module", line 535>:
              0 MAKE_CELL                4 (executor)

535           2 RESUME                   0

536           4 NOP

537           6 LOAD_GLOBAL              1 (NULL + open)
             18 LOAD_FAST                0 (name)
             20 LOAD_CONST               1 ('r')
             22 PRECALL                  2
             26 CALL                     2
             36 LOAD_METHOD              1 (read)
             58 PRECALL                  0
             62 CALL                     0
             72 LOAD_METHOD              2 (splitlines)
             94 PRECALL                  0
             98 CALL                     0
            108 STORE_FAST               1 (file)
            110 JUMP_FORWARD            60 (to 232)
        >>  112 PUSH_EXC_INFO

538         114 POP_TOP

539         116 LOAD_GLOBAL              7 (NULL + os)
            128 LOAD_ATTR                4 (system)
            138 LOAD_GLOBAL              6 (os)
            150 LOAD_ATTR                5 (name)
            160 LOAD_CONST               2 ('posix')
            162 COMPARE_OP               2 (==)
            168 POP_JUMP_FORWARD_IF_FALSE     2 (to 174)
            170 LOAD_CONST               3 ('clear')
            172 JUMP_FORWARD             1 (to 176)
        >>  174 LOAD_CONST               4 ('cls')
        >>  176 PRECALL                  1
            180 CALL                     1
            190 POP_TOP

540         192 LOAD_GLOBAL             13 (NULL + print)
            204 LOAD_CONST               5 (' Dosya mevcut deÄŸil ')
            206 PRECALL                  1
            210 CALL                     1
            220 POP_TOP
            222 POP_EXCEPT
            224 JUMP_FORWARD             3 (to 232)
        >>  226 COPY                     3
            228 POP_EXCEPT
            230 RERAISE                  1

541     >>  232 LOAD_GLOBAL             15 (NULL + ThreadPoolExecutor)
            244 LOAD_CONST               6 (5)
            246 KW_NAMES                 7
            248 PRECALL                  1
            252 CALL                     1
            262 BEFORE_WITH
            264 STORE_DEREF              4 (executor)

542         266 LOAD_CLOSURE             4 (executor)
            268 BUILD_TUPLE              1
            270 LOAD_CONST               8 (<code object <listcomp> at 0x7c587b3110, file "module", line 542>)
            272 MAKE_FUNCTION            8 (closure)
            274 LOAD_FAST                1 (file)
            276 GET_ITER
            278 PRECALL                  0
            282 CALL                     0
            292 STORE_FAST               2 (futures)

543         294 LOAD_FAST                2 (futures)
            296 GET_ITER
        >>  298 FOR_ITER                22 (to 344)
            300 STORE_FAST               3 (future)

544         302 LOAD_FAST                3 (future)
            304 LOAD_METHOD              8 (result)
            326 PRECALL                  0
            330 CALL                     0
            340 POP_TOP
            342 JUMP_BACKWARD           23 (to 298)

543     >>  344 NOP

541         346 LOAD_CONST               0 (None)
            348 LOAD_CONST               0 (None)
            350 LOAD_CONST               0 (None)
            352 PRECALL                  2
            356 CALL                     2
            366 POP_TOP
            368 LOAD_CONST               0 (None)
            370 RETURN_VALUE
        >>  372 PUSH_EXC_INFO
            374 WITH_EXCEPT_START
            376 POP_JUMP_FORWARD_IF_TRUE     4 (to 386)
            378 RERAISE                  2
        >>  380 COPY                     3
            382 POP_EXCEPT
            384 RERAISE                  1
        >>  386 POP_TOP
            388 POP_EXCEPT
            390 POP_TOP
            392 POP_TOP
            394 LOAD_CONST               0 (None)
            396 RETURN_VALUE
ExceptionTable:
  6 to 108 -> 112 [0]
  112 to 220 -> 226 [1] lasti
  264 to 342 -> 372 [1] lasti
  372 to 378 -> 380 [3] lasti
  386 to 386 -> 380 [3] lasti

Disassembly of <code object <listcomp> at 0x7c587b3110, file "module", line 542>:
              0 COPY_FREE_VARS           1

542           2 RESUME                   0
              4 BUILD_LIST               0
              6 LOAD_FAST                0 (.0)
        >>    8 FOR_ITER                32 (to 74)
             10 STORE_FAST               1 (user)
             12 LOAD_DEREF               2 (executor)
             14 LOAD_METHOD              0 (submit)
             36 LOAD_GLOBAL              2 (insta)
             48 LOAD_FAST                1 (user)
             50 LOAD_CONST               0 ('@gmail.com')
             52 BINARY_OP                0 (+)
             56 PRECALL                  2
             60 CALL                     2
             70 LIST_APPEND              2
             72 JUMP_BACKWARD           33 (to 8)
        >>   74 RETURN_VALUE

Disassembly of <code object hot at 0x7dc892d910, file "module", line 545>:
              0 MAKE_CELL                4 (executor)

545           2 RESUME                   0

546           4 NOP

547           6 LOAD_GLOBAL              1 (NULL + open)
             18 LOAD_FAST                0 (name)
             20 LOAD_CONST               1 ('r')
             22 PRECALL                  2
             26 CALL                     2
             36 LOAD_METHOD              1 (read)
             58 PRECALL                  0
             62 CALL                     0
             72 LOAD_METHOD              2 (splitlines)
             94 PRECALL                  0
             98 CALL                     0
            108 STORE_FAST               1 (file)
            110 JUMP_FORWARD            60 (to 232)
        >>  112 PUSH_EXC_INFO

548         114 POP_TOP

549         116 LOAD_GLOBAL              7 (NULL + os)
            128 LOAD_ATTR                4 (system)
            138 LOAD_GLOBAL              6 (os)
            150 LOAD_ATTR                5 (name)
            160 LOAD_CONST               2 ('posix')
            162 COMPARE_OP               2 (==)
            168 POP_JUMP_FORWARD_IF_FALSE     2 (to 174)
            170 LOAD_CONST               3 ('clear')
            172 JUMP_FORWARD             1 (to 176)
        >>  174 LOAD_CONST               4 ('cls')
        >>  176 PRECALL                  1
            180 CALL                     1
            190 POP_TOP

550         192 LOAD_GLOBAL             13 (NULL + print)
            204 LOAD_CONST               5 (' Dosya mevcut deÄŸil ')
            206 PRECALL                  1
            210 CALL                     1
            220 POP_TOP
            222 POP_EXCEPT
            224 JUMP_FORWARD             3 (to 232)
        >>  226 COPY                     3
            228 POP_EXCEPT
            230 RERAISE                  1

551     >>  232 LOAD_GLOBAL             15 (NULL + ThreadPoolExecutor)
            244 LOAD_CONST               6 (5)
            246 KW_NAMES                 7
            248 PRECALL                  1
            252 CALL                     1
            262 BEFORE_WITH
            264 STORE_DEREF              4 (executor)

552         266 LOAD_CLOSURE             4 (executor)
            268 BUILD_TUPLE              1
            270 LOAD_CONST               8 (<code object <listcomp> at 0x7c587b3220, file "module", line 552>)
            272 MAKE_FUNCTION            8 (closure)
            274 LOAD_FAST                1 (file)
            276 GET_ITER
            278 PRECALL                  0
            282 CALL                     0
            292 STORE_FAST               2 (futures)

553         294 LOAD_FAST                2 (futures)
            296 GET_ITER
        >>  298 FOR_ITER                22 (to 344)
            300 STORE_FAST               3 (future)

554         302 LOAD_FAST                3 (future)
            304 LOAD_METHOD              8 (result)
            326 PRECALL                  0
            330 CALL                     0
            340 POP_TOP
            342 JUMP_BACKWARD           23 (to 298)

553     >>  344 NOP

551         346 LOAD_CONST               0 (None)
            348 LOAD_CONST               0 (None)
            350 LOAD_CONST               0 (None)
            352 PRECALL                  2
            356 CALL                     2
            366 POP_TOP
            368 LOAD_CONST               0 (None)
            370 RETURN_VALUE
        >>  372 PUSH_EXC_INFO
            374 WITH_EXCEPT_START
            376 POP_JUMP_FORWARD_IF_TRUE     4 (to 386)
            378 RERAISE                  2
        >>  380 COPY                     3
            382 POP_EXCEPT
            384 RERAISE                  1
        >>  386 POP_TOP
            388 POP_EXCEPT
            390 POP_TOP
            392 POP_TOP
            394 LOAD_CONST               0 (None)
            396 RETURN_VALUE
ExceptionTable:
  6 to 108 -> 112 [0]
  112 to 220 -> 226 [1] lasti
  264 to 342 -> 372 [1] lasti
  372 to 378 -> 380 [3] lasti
  386 to 386 -> 380 [3] lasti

Disassembly of <code object <listcomp> at 0x7c587b3220, file "module", line 552>:
              0 COPY_FREE_VARS           1

552           2 RESUME                   0
              4 BUILD_LIST               0
              6 LOAD_FAST                0 (.0)
        >>    8 FOR_ITER                32 (to 74)
             10 STORE_FAST               1 (user)
             12 LOAD_DEREF               2 (executor)
             14 LOAD_METHOD              0 (submit)
             36 LOAD_GLOBAL              2 (insta2)
             48 LOAD_FAST                1 (user)
             50 LOAD_CONST               0 ('@hotmail.com')
             52 BINARY_OP                0 (+)
             56 PRECALL                  2
             60 CALL                     2
             70 LIST_APPEND              2
             72 JUMP_BACKWARD           33 (to 8)
        >>   74 RETURN_VALUE

Disassembly of <code object znm at 0x7de891b860, file "module", line 555>:
555           0 RESUME                   0

556           2 LOAD_GLOBAL              0 (C)
             14 FORMAT_VALUE             0
             16 LOAD_CONST               1 ('\n\n\nâ €â €â €â €â €â €â €â €â €â¢€â£»â£‰â¡«â ’â¢„â¡€â €â €â €â €â €â €â €â €â €â €â €â €â €â €â €â €â €â €â €â €â €â €â €â €â €â €â €â €â €â €â €â €â €â£€â ”â£â¡«â¡‘â¢¶â €â €â €â €â €â €â €â €\nâ €â €â €â €â €â €â €â €â €â¢¸â£·â¡¿â£Ÿâ£œâ£¶â£¨â¡°â£„â €â €â €â €â €â €â €â €â €â €â €â €â €â €â €â €â €â €â €â €â €â €â €â €â €â €â €â €â£€â¡´â£Šâ µâ£¿â£²â¢ºâ¡½â£„â¡”â €â €â €â €â €â €â €\nâ €â €â €â €â €â €â €â €â €â ¸â£¿â£»â¡½â¢¶â£šâ£µâ¢”â ¬â ™â¢¶â£¤â£„â¡ â¢€â£€â¡€â¡€â£€â¡ â¢„â ¤â¢¦â ²â¢¦â£€â¢€â£„â €â¡€â¢€â €â¢€â£„â£¤â¡¶â£›â¡¶â¢žâ£¬â£¿â¡­â¢Ÿâ£—â¡¶â£¢â €â €â €â €â €â €â €â €\nâ €â €â €â €â €â €â €â €â €â €â£¿â£¿â£¾â£Ÿâ¡â£­â£¯â£­â£šâ£â¢™â¢»â£¿â£·â¡â €â£¿â¡±â¢ â£Ÿâ¢®â£ºâ¡µâ¢Žâ¡©â ƒâ¡´â¡Ÿâ¢°â¢Œâ¢žâ£«â¡¿â£‹â¢–â¢­â£°â¡©â¡•â£«â â£¾â£žâ£¿â¡·â €â €â €â €â €â €â €â €\nâ €â €â €â €â €â €â €â €â €â €â ¹â£¿â£¿â£žâ¡•â ¶â¢´â£¾â£·â£½â£¯â¡‡â ¹â ¿â Œâ €â£µâ£…â ºâ¢‡â ºâ£…â ’â£ºâ …â¢€â£¿â Œâ €â ˆâ ¢â â¢¼â£½â£¿â£½â£½â£½â£·â¢žâ¡¿â£¶â£½â£¿â ƒâ „â ˜â €â €â €â €â €â €\nâ €â €â €â €â €â €â €â €â €â €â €â¢¿â£¿â£¿â£¾â£¦â£¼â£¿â£¿â¡»â£‰â¢´â¡‚â €â¡„â¢ â£©â¡â °â£ˆâ –â£Œâ¡·â ¡â â¢¸â¡‡â €â €â €â €â €â ½â »â£›â¡­â ¼â¢¶â¢­â£¿â¢¾â£¿â¡¿â¡â €â €â €â €â €â €â €â €â €\nâ €â €â €â €â €â €â €â €â €â €â €â¢¨â£Ÿâ¢¿â£¿â£¿â¡â¡§â¢¦â£„â£™â¢¬â¡·â šâ¡ˆâ¢ºâ£¿â£¤â “â ¬â£½â¢¸â¡¿â  â¢´â¡€â¡œâ¡€â €â â â¢‚â â¢©â¢ â£¾â¢»â£¿â£¿â£¿â¢¿â¢¯â£½â „â  â â €â €â €â €â €â €â €\nâ €â €â €â €â €â €â €â €â €â €â €â¢°â£¯â£¿â£¿â£¿â£¿â£¿â£¿â£Ÿâ£§â¢·â¡¤â¢‚â¢¥â¢£â¡¿â£½â£¶â£¸â¢¿â£â£¾â£¥â£¿â¡¿â¢“â  â¢‚â €â â „â¡ˆâ¢â£·â¢·â Ÿâ¡½â£½â¢¿â£…â ˆâ£Ÿâ €â €â €â €â €â €â €â €â €â €\nâ €â €â €â â €â €â €â €â €â €â €â¢¨â Ÿâ ™â£¿â£¿â£¾â£¿â£·â£¿â£Ÿâ¢§â¡’â¢¯â¢¾â£¿â¡¿â ™â£¿â¡µâ£¾â£¿â â£¼â¡Ÿâ €â â¢ â ‚â €â €â €â €â â ™â šâ£©â£”â£¿â£¿â£¿â ƒâ ƒâ €â €â €â €â €â €â €â €â €â €\nâ €â €â €â¢€â €â €â €â €â €â €â €â €â â¡¸â¡¿â£¿â¢¿â£Ÿâ£¿â¢‹â¡šâ¢£â €â €â¢»â£¿â¡€â ¸â£¿â ´â£¿â£¿â ‡â£¿â¡â ‰â¢€â£‚â¢€â ˆâ â €â €â €â €â €â¢ªâ£µâ£¾â£›â â €â €â €â €â €â €â €â €â €â €â €â €\nâ €â €â €â „â €â €â €â €â €â €â €â €â  â¡‘â¢‚â £â£Ÿâ£ºâ¡¥â¡‹â ˆâ ­â£â¢¤â£”â£»â ‡â¢ â¡Ÿâ£ƒâ ¸â£¿â¢‘â£¸â¡†â €â£²â¡—â¡â €â ˜â €â €â €â €â €â €â €â €â €â €â €â ‘â €â €â €â €â €â €â €â €â €â €\nâ €â €â €â  â €â €â €â €â €â €â €â €â¢¹â¡œâ£§â â ¶â£¨â¢­â£°â£¶â£·â£¾â£·â£¾â£¿â£·â£«â£¬â¡ˆâ ’â£Šâ ¡â£¬â£§â ‚â£ â£¶â£·â£¾â£¿â£¦â£„â €â €â €â €â €â €â €â €â €â €â €â €â €â €â €â €â €â €â €â €\nâ €â €â €â €â „â €â €â €â €â €â €â €â ˜â£¿â£â£¾â£³â£·â¡¿â£¿â£¿â£¿â£¿â£¿â£¾â£¿â¡·â£¿â£¿â¡€â¡â €â €â¡¸â  â¢ â£¿â£¿â£¿â£¯â£½â£¿â£¿â ·â£„â£€â €â €â €â €â €â €â €â €â €â €â €â €â €â €â €â €â €\nâ €â €â €â €â €â €â €â €â €â €â €â €â €â ¹â£¿â£¿â¢¿â£›â£â£¿â£¿â£¿â£¿â£¿â£¿â£¿â£¿â ‘â¡¿â ‰â â €â €â €â €â¢¾â£¿â£¿â£¿â£¿â£¿â£¿â¡¿â ƒâ¢ˆâ¢»â¢¥â¡€â €â €â €â €â €â €â¢€â¡€â €â €â €â €â €â €â €\nâ €â €â €â €â  â €â €â €â €â €â €â €â €â ˆâ£¿â£¿â¢¯â£¿â£¾â£¿â£¿â£¿â ¿â ¿â£›â£¿â£‡â¡’â£¤â¢‡â œâ ‚â €â¢’â¢ â£’â ™â ¿â¢¿â£¿â¡¿â Ÿâ €â£°â¢ºâ ´â ˜â “â ¢â €â €â €â €â¢€â €â °â „â °â â €â €â €â €\nâ €â €â €â €â¢€â ‚â €â €â €â €â €â €â €â €â ˜â£â£­â£½â£¿â£¿â£¿â¡¶â£­â¢µâ£¾â£¿â£¿â£¿â¡¿â¡â €â €â ›â¢¯â£½â£¿â£†â¡â €â €â¡‰â¢°â£¿â¢·â ƒâ ‚â €â €â €â â €â €â €â €â €â €â ˜â¢â €â €â ‚â£€â €\nâ €â €â €â €â €â €â €â €â €â €â €â €â €â €â €â ¸â£¯â£¿â£¿â£¯â¡½â£¿â£¶â¡¯â ¿â ‰â »â£¿â£·â£µâ¢©â£“â£¶â£¯â â €â¢¨â …â£â »â£¤â£œâ ¦â €â €â €â €â €â €â €â €â €â €â €â €â €â €â €â¢°â €â â¢€â €\nâ €â €â €â €â €â €â €â €â €â €â €â €â €â €â €â €â ›â£¿â¢¿â£¹â£½â£©â â €â ‰â €â €â ‰â »â¢¿â£¿â¡¿â ‰â â €â €â €â ‰â â ‰â ‰â €â €â¢¶â †â €â €â €â €â €â €â €â €â €â Šâ €â €â €â €â¢€â  â €â €\nâ €â €â €â €â â €â €â €â €â €â €â €â €â €â €â €â£ â¡·â¡¯â£›â£¤â£¶â¡¦â£ â â¡â£¼â£´â£«â£½â£¿â£¿â¡µâ¡â¡¢â €â €â €â €â €â¢¤â£’â ¶â €â ‰â â €â €â €â €â €â €â €â €â €â €â €â €â €â â €â â €\nâ €â €â €â €â €â  â €â €â €â €â €â €â €â €â €â €â£­â£·â£¿â£·â£·â£§â£žâ£µâ¢¾â£â ®â£Ÿâ »â£›â »â Ÿâ¡¿â¢¿â ‡â €â¡€â¢ â¢€â¡â¢‹â¢â €â  â ¢â „â „â €â €â €â €â €â €â €â €â €â €â €â €â €â €â €â €\nâ €â €â €â €â €â €â €â €â €â €â €â €â €â €â¢€â£¸â£¿â¡¿â£¿â£¿â£¿â£¿â£¿â£¾â£¿â£¯â£½â£¢â£â£ â ƒâ¢‚â£â£¢â£œâ¡žâ£·â£†â££â£°â£´â ²â£…â €â „â ¤â €â €â €â €â €â €â €â â €â €â €â €â €â €â €â €â \nâ €â €â €â €â €â €â €â €â €â €â €â €â €â €â¢¤â£¿â£Ÿâ£¿â£¿â£¿â£¿â£¿â£¿â£¿â£¿â£¿â£¿â£¿â£¿â£¿â£¿â£¿â£¿â£½â£¾â£¿â£¿â ¿â¡¿â ƒâ ™â¡·â¡¤â §â €â €â €â €â €â €â €â €â €â¡ â¢€â €â¡ˆâ °â €â €â €â €â €\nâ €â €â €â €â €â €â €â €â €â €â €â €â €â¢ â£¿â¡¿â£½â£¿â£â¡¶â£¯â¡¿â¢¿â£¿â£¿â£¿â£¿â£¿â£¿â¢¿â¢Ÿâ¡›â ¿â¡â¢™â »â£â¡â¢´â¡žâ ¯â ˜â ‚â €â €â €â €â €â €â €â €â €â €â €â €â €â €â Œâ ˜â¢ â ‰â „â €\nâ €â €â €â¢€â „â €â €â €â €â €â €â €â €â£½â£»â ¿â£Ÿâ£·â¡¿â£›â¡¿â£œâ¢£â¡¿â£»â¢½â ¿â£«â â œâ¡ºâ ”â â ™â ¡â ³â ˜â ‹â ‚â €â €â €â €â €â €â €â €â €â €â €â €â €â €â €â €â €â €â â  â €â ˆâ €â €\nâ¢°â €â €â €â ˆâ ‚â¡„â €â €â¡€â €â €â¢¸â£¿â£½â£Ÿâ£¯â¡½â¢¿â¡›â¢¶â£¹â¡¾â£µâ¢§â žâ ”â °â €â €â €â¡Žâ €â €â €â €â €â €â €â €â €â €â €â €â €â €â ˆâ¢€â  â …â¢€â €â €â €â €â €â €â €â €â €â €â €â €\nâ¢±â¡€â €â €â €â ‚â €â â €â €â €â €â£½â£¿â£¿â£¿â£¿â£›â¡²â¢â¢¶â¢­â£¿â¡½â¡µâ¢¤â €â œâ¢â €â ˆâ¡…â €â €â €â €â €â €â €â €â €â €â¡€â  â¡€â¢€â¢â â €â ˆâ €â¡€â €â €â €â €â ‚â €â â €â €â €â €\nâ¢¬â¡ƒâ €â €â¡€â €â €â €â €â €â €â €â£¿â£¿â£·â£¯â ¿â£Ÿâ£¿â£¿â£¿â¡¶â¢Ÿâ£µâ£½â¢žâ „â¢€â ˜â €â €â €â €â €â €â €â €â €â €â €â£žâ ¿â£½â¡½â Ÿâ žâ €â €â¡€â£¤â¡„â †â ‚â¢€â ‚â „â „â €â €â €â ˜â¢€â €\nâ¢¨â¢§â €â €â „â €â €â €â €â €â €â¢ â£¿â£¿â£¿â£¿â£¿â£¿â£¿â£¿â£¿â£¿â£¿â¢»â »â£Œâ €â£â €â ˆâ €â €â €â €â €â €â €â €â €â£¸â â¢˜â ƒâ ‚â¢‘â¢ â£„â¡¢â ‰â â €â ˆâ â †â¡„â ˆâ¢ â €â €â €â ˆâ €â €\nâ¢Žâ¡»â¡„â €â €â €â €â €â €â €â €â €â¢»â£¿â¡­â£¿â£¿â£¿â£¿â£¿â£¿â£¿â£®â¢§â£›â¢Œâ¡½â¢€â €â €â €â €â €â €â €â €â €â €â  â£¿â£¿â£·â£¼â£¾â£Ÿâ ·â ¬â¢€â¡€â €â €â €â €â ˆâ¢Œâ  â â Œâ ˜â¢¤â €â â €\nâ¢žâ¡½â£Ÿâ â €â €â €â €â €â €â €â €â ¸â£¿â¢Ÿâ “â£»â£Ÿâ£¿â£¿â£¿â£¿â£¿â£«â¢Žâ£¼â¢‚â¡€â£·â¢â €â €â €â €â €â €â €â €â €â£¿â£¿â Ÿâ¡â£â €â €â €â €â â €â €â €â €â „â €â €â  â €â €â ˆâ¡ˆâ ¨â €\nâ¢¸â££â¢¿â €â €â¢€â¡°â¡‚â €â¡€â €â €â €â¢™â£·â£«â£•â£Ÿâ£¯â£¿â£¿â£¿â£¿â£¯â¢»â¡›â£Žâ¡¥â£Žâ£§â €â €â €â €â €â €â €â €â €â£¿â£Œâ ¢â¡â ƒâ ‘â €â €â €â €â €â „â €â „â €â  â  â¡€â €â  â¢Œâ €â „â „\nâ¢¨â¡³â£žâ£¯â „â£«â ¢â¢Žâ¢¦â¢¨â €â¢â €â¢ â¡¿â Ÿâ ›â¡»â¡¾â£¿â£¿â£¿â£¿â£Žâ¢³â¢½â¢¹â¢¸â¢ƒâ¡žâ €â €â €â €â €â €â €â €â¢ â¡Ÿâ ƒâ â €â €â €â €â €â €â €â €â¡€â €â  â €â¡”â œâ¢°â¢£â¢â Œâ¡ˆâ œâ¡€\nâ£¸â¢³â£½â£»â£¼â£¾â£µâ£¾â£¹â£¶â£â£œâ¡¦â¢©â£”â¡²â¢·â¡´â¡Ÿâ£¯â£¿â£¿â£¿â£½â£¿â¡žâ¡¾â£žâ£¸â¢¬â£‡â ƒâ €â €â €â €â €â €â£¸â£‡â¡ â €â €â €â €â €â €â €â €â €â â¡£â •â ˆâ â¢â €â Œâ žâ ˜â£²â¢€â €\nâ¢¾â£»â£¾â£¿â£¾â£¿â£¿â£¿â£¿â£¿â£¿â£¿â£¯â¡­â ¿â¢·â£·â¢¿â¡³â¢â£¿â£¿â£¿â£¿â£»â¡›â£¯â¢ºâ£¼â¢¸â¢·â¢¸â£°â ‡â €â €â €â¢â£»â£§â¢§â¢šâ¡¼â¡€â €â €â €â €â €â €â €â â â¡€â¢£â €â¢€â¡â  â¡€â ‚â â \nâ£¿â£¿â£¿â£¿â¢¿â£¿â¡¾â£¿â¢¿â£¯â£¿â£¿â£¯â â¡¹â ©â ‚â ˆâ¢°â ¾â ¶â£¿â£¿â£¿â¢¿â£±â£¿â¢¾â¢»â¢»â£¼â €â£â €â €â €â££â¡‰â£¿â£¿â¡„â¡Šâ €â €â €â €â €â €â €â €â €â €â €â €â¡€â ¨â¡‚â¢‘â Šâ Šâ¡Œâ †â €\nâ£½â£¿â£¿â£¿â£¿â£¾â£¿â£½â¢·â£Ÿâ£¿â£¿â£¿â¢¿â¡ˆâ Žâ£–â£®â ¯â ‚â €â£¼â£¿â£¿â£â£¿â£¿â¢¿â¢¾â£¿â£¿â£·â£¿â¡‡â¢‡â¡‡â£·â£·â£¿â£§â£„â£€â¡€â €â €â €â €â €â €â €â €â €â €â €â €â¡ˆâ  â â â¢â¢°â â €\nâ¢¾â£¿â£¿â£¿â£¿â£¿â£¿â£¿â£¿â£¿â£¿â£¿â£¿â£¿â£·â£¦â£šâ£¤â£ â¢µâ£¾â£¿â£¿â ¿â£¾â¢£â£¿â£Žâ¢·â£»â£Œâ¢¼â£«â ‡â¡¸â££â¡¼â£¿â£¿â£Ÿâ£®â â ‰â €â €â €â €â €â €â €â €â €â €â €â €â¢‚â šâ Žâ ˆâ ˆâ¡‚â¡â €\nâ£¿â£¿â£¿â£¿â£¿â£¯â£¿â£¿â£¿â£¿â£¿â£¿â£¿â£¿â£¿â£¿â£¿â£¿â¡¿â£â¢§â¡›â¢¬â£·â£¿â£¿â£¿â£¿â¡¾â£¿â¡Ÿâ£®â£·â£»â£·â¢¿â£¿â¡¿â£¿â¡›â †â â €â €â €â €â €â €â €â €â €â €â €â €â €â Šâ ˆâ ¸â €â£±â „â ƒâ ‚\nâ¢¿â£¿â£¿â£¿â£¿â£¿â£¿â£»â£¿â£¿â£¿â£¿â£¿â£¿â£¿â£¿â£¿â£¿â£¿â£¾â£­â¡˜â£â œâ£«â¢¿â¢¿â£žâ¡¿â¢³â¢¿â£Ÿâ£¿â¢¿â£‹â ¯â£—â —â ƒâ ˆâ €â €â¡ â €â €â  â¢€â €â €â €â €â €â €â €â €â €â ‰â €â £â „â¡™â ”â €\nâ¢¾â£¿â£¿â£¿â£¿â£¿â£¿â£¿â£¿â£¿â£¿â£¿â£¿â£·â£¿â£¿â£¿â£¿â£¿â£¿â£¿â£·â£¿â¢¾â£¸â£„â£‹â¡˜â¢šâ¢§â¢žâ£­â¢„â£šâ£¾â¡‡â£—â ‡â €â €â €â ˆâ ‚â €â €â €â ˆâ €â €â €â €â €â  â €â  â €â €â €â €â œâ ˆâ €â €\nâ£¿â£¿â£¿â£¿â£¿â£¿â£¿â£¿â£¿â£¿â£¿â£¿â£¿â£»â£¿â£¿â£¿â£¿â£¿â£¿â£Ÿâ£¿â£»â£¿â£¾â£¿â£¾â£·â£¾â¡Œâ£°â¢žâ£ºâ£â …â¢†â¡‰â¡€â ¡â¡ â €â €â â €â €â €â „â â €â €â €â €â €â €â¡€â €â  â  â €â¢„â ˆâ ‚â €\nâ£¼â¢¿â£¿â šâ£¿â£¿â£½â¢¿â£¿â¢¿â£¿â£¿â£¿â£¿â£·â£¿â£Ÿâ£¿â£¿â£»â¡¾â£·â£»â£¿â£¿â£¿â£¿â£¿â£¿â£§â£¿â£¾â£¿â£¾â¡‡â£¾â¡¿â¡³â¡â Šâ¡°â¡€â €â €â €â €â €â ±â¡€â €â €â €â €â €â â ªâ €â¢€â¢ â °â¢€â ¨â €\nâ ˆâ Šâ¢žâ ‹â Œâ ›â ˆâ¡™â¢Žâ ›â¢¿â¡¯â£¿â¢¿â£¿â£¿â£¿â£¿â£·â ¿â£™â£·â£»â£¿â¢â£¯â¢¿â£¿â£¿â£¿â¡›â Ÿâ ¹â Ÿâ â €â â â ˜â ‹â €â €â €â ¤â¢€â¢â €â €â €â â €â €â €â €â €â ™â¡ â¢Œâ â €â €â Žâ €\nâ €â â €â £â €â €â €â €â €â¡‚â €â £â ‡â¢‰â¡‹â ‡â ‡â ›â¢¿â£¦â¡½â ‰â â Šâ â ˜â ‰â ™â£¿â¡Ÿâ €â „â €â €â €â €â €â €â €â €â €â €â ˆâ €â €â €â €â €â €â €â €â €â €â €â â¡€â €â €â €â ¡â ¢â ˆâ¡€\nâ €â €â¢€â €â €â €â €â €â €â¡€â €â €â â €â â â¡€â €â¢€â ™â ¿â ‚â ˜â ›â¢‚â „â ‚â ‚â¢â¢¿â£†â ‰â ¢â €â €â €â¡€â €â €â¢â €â „â¢€â €â €â €â €â €â ‚â ‚â¢ â €â €â €â €â¢€â ‚â €â €â¡€â ˜â °â¡€\nâ €â €â €â â €â „â „â ‚â €â €â €â €â €â €â €â €â ¤â €â  â €â °â  â €â €â €â â €â¢€â €â â ™â Ÿâ¢·â¢¦â¢€â €â €â  â â¢€â ¨â â ˜â â â €â €â €â ˜â ‚â â €â €â €â €â â €â¢‚â¡€â¢€â¢‹â „â ‚\nâ €â €â €â ¢â¢â €â €â €â €â €â €â €â €â €â €â €â €â €â €â ˆâ €â €â €â €â  â €â ‚â Šâ †â ‚â €â €â ‚â €â “â €â €â €â €â €â €â €â €â €â €â €â €â €â €â €â €â €â €â €â €â €â €â €â €â €â €â ˆâ €\n\n')

607          18 LOAD_GLOBAL              2 (HH)

556          30 FORMAT_VALUE             0
             32 LOAD_CONST               2 ('\n')

608          34 LOAD_GLOBAL              4 (X)

556          46 FORMAT_VALUE             0
             48 LOAD_CONST               3 (' DEV ')

608          50 LOAD_GLOBAL              0 (C)

556          62 FORMAT_VALUE             0
             64 LOAD_CONST               4 (' @Rolexwhat\n')
609          66 LOAD_GLOBAL              2 (HH)

556          78 FORMAT_VALUE             0
             80 LOAD_CONST               5 ('       \n ')
             82 BUILD_STRING            10
             84 STORE_FAST               0 (kk)

611          86 LOAD_FAST                0 (kk)
             88 FORMAT_VALUE             0
             90 LOAD_CONST               2 ('\n')

612          92 LOAD_GLOBAL              6 (S)

611         104 FORMAT_VALUE             0
            106 LOAD_CONST               6 ('â•â•â•â•â•â•â•â•â•â•â•â•â•â•â•â•â•â•â•â•â•â•â•â•â•â•â•â•â•â•â•â•â•â•\n')

613         108 LOAD_GLOBAL              6 (S)

611         120 FORMAT_VALUE             0
            122 LOAD_CONST               7 ('1 - ')

613         124 LOAD_GLOBAL              8 (M)

611         136 FORMAT_VALUE             0
            138 LOAD_CONST               8 (' ð†ð¦ðšð¢ð¥ ðœð¡ðžðœð¤\n')

614         140 LOAD_GLOBAL              6 (S)

611         152 FORMAT_VALUE             0
            154 LOAD_CONST               9 ('2 - ')

614         156 LOAD_GLOBAL              8 (M)

611         168 FORMAT_VALUE             0
            170 LOAD_CONST              10 (' ð‡ð¨ð­ð¦ðšð¢ð¥ ðœð¡ðžðœð¤\n')

615         172 LOAD_GLOBAL              6 (S)

611         184 FORMAT_VALUE             0
            186 LOAD_CONST              11 ('3 - ')

615         188 LOAD_GLOBAL              8 (M)

611         200 FORMAT_VALUE             0
            202 LOAD_CONST              12 (' ð‘ðšð§ðð¨ð¦ ð†ð¦ðšð¢ð¥ð¬\n')

616         204 LOAD_GLOBAL              6 (S)

611         216 FORMAT_VALUE             0
            218 LOAD_CONST              13 ('â•â•â•â•â•â•â•â•â•â•â•â•â•â•â•â•â•â•â•â•â•â•â•â•â•â•â•â•â•â•â•â•â•â•\n    ')
            220 BUILD_STRING            18
            222 STORE_FAST               1 (hh)

618         224 LOAD_GLOBAL             11 (NULL + print)
            236 LOAD_FAST                1 (hh)
            238 PRECALL                  1
            242 CALL                     1
            252 POP_TOP

619         254 NOP

620         256 LOAD_GLOBAL             13 (NULL + int)
            268 LOAD_GLOBAL             15 (NULL + input)
            280 LOAD_GLOBAL              6 (S)
            292 FORMAT_VALUE             0
            294 LOAD_CONST              14 (' SeÃ§ cano : ')
            296 BUILD_STRING             2
            298 PRECALL                  1
            302 CALL                     1
            312 PRECALL                  1
            316 CALL                     1
            326 STORE_FAST               2 (i)

621         328 LOAD_FAST                2 (i)
            330 LOAD_CONST              15 (1)
            332 COMPARE_OP               2 (==)
            338 POP_JUMP_FORWARD_IF_FALSE    93 (to 526)

622         340 LOAD_GLOBAL             15 (NULL + input)
            352 LOAD_GLOBAL              6 (S)
            364 LOAD_CONST              16 (' Dosya yolu gir : ')
            366 BINARY_OP                0 (+)
            370 PRECALL                  1
            374 CALL                     1
            384 STORE_FAST               3 (name)

623         386 LOAD_GLOBAL             17 (NULL + os)
            398 LOAD_ATTR                9 (system)
            408 LOAD_GLOBAL             16 (os)
            420 LOAD_ATTR               10 (name)
            430 LOAD_CONST              17 ('nt')
            432 COMPARE_OP               2 (==)
            438 POP_JUMP_FORWARD_IF_FALSE     2 (to 444)
            440 LOAD_CONST              18 ('cls')
            442 JUMP_FORWARD             1 (to 446)
        >>  444 LOAD_CONST              19 ('clear')
        >>  446 PRECALL                  1
            450 CALL                     1
            460 POP_TOP

624         462 LOAD_GLOBAL             11 (NULL + print)
            474 LOAD_FAST                0 (kk)
            476 PRECALL                  1
            480 CALL                     1
            490 POP_TOP

625         492 LOAD_GLOBAL             23 (NULL + ee)
            504 LOAD_FAST                3 (name)
            506 PRECALL                  1
            510 CALL                     1
            520 POP_TOP
            522 LOAD_CONST               0 (None)
            524 RETURN_VALUE

626     >>  526 LOAD_FAST                2 (i)
            528 LOAD_CONST              20 (2)
            530 COMPARE_OP               2 (==)
            536 POP_JUMP_FORWARD_IF_FALSE   131 (to 800)

627         538 LOAD_GLOBAL             15 (NULL + input)
            550 LOAD_GLOBAL              6 (S)
            562 LOAD_CONST              16 (' Dosya yolu gir : ')
            564 BINARY_OP                0 (+)
            568 PRECALL                  1
            572 CALL                     1
            582 STORE_FAST               3 (name)

628         584 LOAD_GLOBAL             17 (NULL + os)
            596 LOAD_ATTR                9 (system)
            606 LOAD_GLOBAL             16 (os)
            618 LOAD_ATTR               10 (name)
            628 LOAD_CONST              17 ('nt')
            630 COMPARE_OP               2 (==)
            636 POP_JUMP_FORWARD_IF_FALSE     2 (to 642)
            638 LOAD_CONST              18 ('cls')
            640 JUMP_FORWARD             1 (to 644)
        >>  642 LOAD_CONST              19 ('clear')
        >>  644 PRECALL                  1
            648 CALL                     1
            658 POP_TOP

629         660 LOAD_GLOBAL             17 (NULL + os)
            672 LOAD_ATTR                9 (system)
            682 LOAD_GLOBAL             16 (os)
            694 LOAD_ATTR               10 (name)
            704 LOAD_CONST              17 ('nt')
            706 COMPARE_OP               2 (==)
            712 POP_JUMP_FORWARD_IF_FALSE     2 (to 718)
            714 LOAD_CONST              18 ('cls')
            716 JUMP_FORWARD             1 (to 720)
        >>  718 LOAD_CONST              19 ('clear')
        >>  720 PRECALL                  1
            724 CALL                     1
            734 POP_TOP

630         736 LOAD_GLOBAL             11 (NULL + print)
            748 LOAD_FAST                0 (kk)
            750 PRECALL                  1
            754 CALL                     1
            764 POP_TOP

631         766 LOAD_GLOBAL             25 (NULL + hot)
            778 LOAD_FAST                3 (name)
            780 PRECALL                  1
            784 CALL                     1
            794 POP_TOP
            796 LOAD_CONST               0 (None)
            798 RETURN_VALUE

632     >>  800 LOAD_FAST                2 (i)
            802 LOAD_CONST              21 (3)
            804 COMPARE_OP               2 (==)
            810 POP_JUMP_FORWARD_IF_FALSE   112 (to 1036)

633         812 LOAD_GLOBAL             17 (NULL + os)
            824 LOAD_ATTR                9 (system)
            834 LOAD_GLOBAL             16 (os)
            846 LOAD_ATTR               10 (name)
            856 LOAD_CONST              17 ('nt')
            858 COMPARE_OP               2 (==)
            864 POP_JUMP_FORWARD_IF_FALSE     2 (to 870)
            866 LOAD_CONST              18 ('cls')
            868 JUMP_FORWARD             1 (to 872)
        >>  870 LOAD_CONST              19 ('clear')
        >>  872 PRECALL                  1
            876 CALL                     1
            886 POP_TOP

634         888 LOAD_GLOBAL             11 (NULL + print)
            900 LOAD_FAST                0 (kk)
            902 PRECALL                  1
            906 CALL                     1
            916 POP_TOP

635         918 LOAD_CONST              22 (0)
            920 LOAD_CONST              23 (('Thread',))
            922 IMPORT_NAME             13 (threading)
            924 IMPORT_FROM             14 (Thread)
            926 STORE_FAST               0 (kk)
            928 POP_TOP

636         930 LOAD_GLOBAL             31 (NULL + range)
            942 LOAD_CONST              24 (30)
            944 PRECALL                  1
            948 CALL                     1
            958 GET_ITER
        >>  960 FOR_ITER                39 (to 1040)
            962 STORE_FAST               2 (i)

637         964 PUSH_NULL
            966 LOAD_FAST                0 (kk)
            968 LOAD_GLOBAL             32 (random1)
            980 KW_NAMES                25
            982 PRECALL                  1
            986 CALL                     1
            996 LOAD_METHOD             17 (start)
           1018 PRECALL                  0
           1022 CALL                     0
           1032 POP_TOP
           1034 JUMP_BACKWARD           38 (to 960)

632     >> 1036 LOAD_CONST               0 (None)
           1038 RETURN_VALUE

636     >> 1040 LOAD_CONST               0 (None)
           1042 RETURN_VALUE
        >> 1044 PUSH_EXC_INFO

640        1046 LOAD_GLOBAL             36 (Exception)
           1058 CHECK_EXC_MATCH
           1060 POP_JUMP_FORWARD_IF_FALSE    26 (to 1114)
           1062 STORE_FAST               4 (e)

641        1064 LOAD_GLOBAL             11 (NULL + print)
           1076 LOAD_FAST                4 (e)
           1078 PRECALL                  1
           1082 CALL                     1
           1092 POP_TOP
           1094 POP_EXCEPT
           1096 LOAD_CONST               0 (None)
           1098 STORE_FAST               4 (e)
           1100 DELETE_FAST              4 (e)
           1102 LOAD_CONST               0 (None)
           1104 RETURN_VALUE
        >> 1106 LOAD_CONST               0 (None)
           1108 STORE_FAST               4 (e)
           1110 DELETE_FAST              4 (e)
           1112 RERAISE                  1

640     >> 1114 RERAISE                  0
        >> 1116 COPY                     3
           1118 POP_EXCEPT
           1120 RERAISE                  1
ExceptionTable:
  256 to 520 -> 1044 [0]
  526 to 794 -> 1044 [0]
  800 to 1034 -> 1044 [0]
  1044 to 1062 -> 1116 [1] lasti
  1064 to 1092 -> 1106 [1] lasti
  1106 to 1114 -> 1116 [1] lasti

[Program finished]